{"country_code":"187","country_name":"Oman","country_iso2":"OM","country_iso3":"OMN","regions":[{"region_code":"2263","region_name":"A Dakhliya","country_code":"187","country_name":"Oman","cities":[{"city_code":"23564","city_name":"Adam","region_code":"2263","region_name":"A Dakhliya","country_code":"187","country_name":"Oman"},{"city_code":"23565","city_name":"Al Hamra","region_code":"2263","region_name":"A Dakhliya","country_code":"187","country_name":"Oman"},{"city_code":"23566","city_name":"Bahla","region_code":"2263","region_name":"A Dakhliya","country_code":"187","country_name":"Oman"},{"city_code":"23567","city_name":"Bid Bid","region_code":"2263","region_name":"A Dakhliya","country_code":"187","country_name":"Oman"},{"city_code":"23568","city_name":"Izki","region_code":"2263","region_name":"A Dakhliya","country_code":"187","country_name":"Oman"},{"city_code":"23569","city_name":"Manah","region_code":"2263","region_name":"A Dakhliya","country_code":"187","country_name":"Oman"},{"city_code":"23570","city_name":"Nizwa (Nazwa)","region_code":"2263","region_name":"A Dakhliya","country_code":"187","country_name":"Oman"},{"city_code":"23571","city_name":"Samail","region_code":"2263","region_name":"A Dakhliya","country_code":"187","country_name":"Oman"}]},{"region_code":"2264","region_name":"A Sharqiya","country_code":"187","country_name":"Oman","cities":[{"city_code":"23572","city_name":"Al Mudhaibi","region_code":"2264","region_name":"A Sharqiya","country_code":"187","country_name":"Oman"},{"city_code":"23573","city_name":"Al Qabil","region_code":"2264","region_name":"A Sharqiya","country_code":"187","country_name":"Oman"},{"city_code":"23574","city_name":"Al Wafi","region_code":"2264","region_name":"A Sharqiya","country_code":"187","country_name":"Oman"},{"city_code":"23575","city_name":"Biddiya","region_code":"2264","region_name":"A Sharqiya","country_code":"187","country_name":"Oman"},{"city_code":"23576","city_name":"Ibra","region_code":"2264","region_name":"A Sharqiya","country_code":"187","country_name":"Oman"},{"city_code":"23577","city_name":"Jalan Bani","region_code":"2264","region_name":"A Sharqiya","country_code":"187","country_name":"Oman"},{"city_code":"23578","city_name":"Masirah","region_code":"2264","region_name":"A Sharqiya","country_code":"187","country_name":"Oman"},{"city_code":"23579","city_name":"Sur","region_code":"2264","region_name":"A Sharqiya","country_code":"187","country_name":"Oman"}]},{"region_code":"2265","region_name":"Al Batnah","country_code":"187","country_name":"Oman","cities":[{"city_code":"23580","city_name":"A Rustaq","region_code":"2265","region_name":"Al Batnah","country_code":"187","country_name":"Oman"},{"city_code":"23581","city_name":"Al Awabi","region_code":"2265","region_name":"Al Batnah","country_code":"187","country_name":"Oman"},{"city_code":"23582","city_name":"Al Khabourah","region_code":"2265","region_name":"Al Batnah","country_code":"187","country_name":"Oman"},{"city_code":"23583","city_name":"Al Masnaah","region_code":"2265","region_name":"Al Batnah","country_code":"187","country_name":"Oman"},{"city_code":"23584","city_name":"As Suwaiq","region_code":"2265","region_name":"Al Batnah","country_code":"187","country_name":"Oman"},{"city_code":"23585","city_name":"Barka","region_code":"2265","region_name":"Al Batnah","country_code":"187","country_name":"Oman"},{"city_code":"23586","city_name":"Liwa","region_code":"2265","region_name":"Al Batnah","country_code":"187","country_name":"Oman"},{"city_code":"23587","city_name":"Nakhal","region_code":"2265","region_name":"Al Batnah","country_code":"187","country_name":"Oman"},{"city_code":"23588","city_name":"Saham","region_code":"2265","region_name":"Al Batnah","country_code":"187","country_name":"Oman"},{"city_code":"23589","city_name":"Shinas","region_code":"2265","region_name":"Al Batnah","country_code":"187","country_name":"Oman"},{"city_code":"23590","city_name":"Sohar","region_code":"2265","region_name":"Al Batnah","country_code":"187","country_name":"Oman"}]},{"region_code":"2266","region_name":"Al Dhahira","country_code":"187","country_name":"Oman","cities":[{"city_code":"23591","city_name":"Al Buraimi","region_code":"2266","region_name":"Al Dhahira","country_code":"187","country_name":"Oman"},{"city_code":"23592","city_name":"Dhank","region_code":"2266","region_name":"Al Dhahira","country_code":"187","country_name":"Oman"},{"city_code":"23593","city_name":"Ibri","region_code":"2266","region_name":"Al Dhahira","country_code":"187","country_name":"Oman"},{"city_code":"23594","city_name":"Mahdha","region_code":"2266","region_name":"Al Dhahira","country_code":"187","country_name":"Oman"},{"city_code":"23595","city_name":"Yanqul","region_code":"2266","region_name":"Al Dhahira","country_code":"187","country_name":"Oman"}]},{"region_code":"2267","region_name":"Al Wusta","country_code":"187","country_name":"Oman","cities":[{"city_code":"23596","city_name":"Al Wusta (1)","region_code":"2267","region_name":"Al Wusta","country_code":"187","country_name":"Oman"}]},{"region_code":"2268","region_name":"Dhofar","country_code":"187","country_name":"Oman","cities":[{"city_code":"23597","city_name":"Al Halaniyat Isl.","region_code":"2268","region_name":"Dhofar","country_code":"187","country_name":"Oman"},{"city_code":"23598","city_name":"Marbat","region_code":"2268","region_name":"Dhofar","country_code":"187","country_name":"Oman"},{"city_code":"23599","city_name":"Muqshin","region_code":"2268","region_name":"Dhofar","country_code":"187","country_name":"Oman"},{"city_code":"23600","city_name":"Salalah","region_code":"2268","region_name":"Dhofar","country_code":"187","country_name":"Oman"},{"city_code":"23601","city_name":"Sudh","region_code":"2268","region_name":"Dhofar","country_code":"187","country_name":"Oman"},{"city_code":"23602","city_name":"Taqah","region_code":"2268","region_name":"Dhofar","country_code":"187","country_name":"Oman"},{"city_code":"23603","city_name":"Thumrait","region_code":"2268","region_name":"Dhofar","country_code":"187","country_name":"Oman"}]},{"region_code":"2269","region_name":"Musandam","country_code":"187","country_name":"Oman","cities":[{"city_code":"23604","city_name":"Al Khasab","region_code":"2269","region_name":"Musandam","country_code":"187","country_name":"Oman"},{"city_code":"23605","city_name":"Bukha","region_code":"2269","region_name":"Musandam","country_code":"187","country_name":"Oman"},{"city_code":"23606","city_name":"Diba","region_code":"2269","region_name":"Musandam","country_code":"187","country_name":"Oman"},{"city_code":"23607","city_name":"Madha","region_code":"2269","region_name":"Musandam","country_code":"187","country_name":"Oman"}]},{"region_code":"2270","region_name":"Muscat","country_code":"187","country_name":"Oman","cities":[{"city_code":"23608","city_name":"A Seeb","region_code":"2270","region_name":"Muscat","country_code":"187","country_name":"Oman"},{"city_code":"23609","city_name":"Bausher","region_code":"2270","region_name":"Muscat","country_code":"187","country_name":"Oman"},{"city_code":"23610","city_name":"Muscat","region_code":"2270","region_name":"Muscat","country_code":"187","country_name":"Oman"},{"city_code":"23611","city_name":"Muttrah","region_code":"2270","region_name":"Muscat","country_code":"187","country_name":"Oman"},{"city_code":"23612","city_name":"Quriyat","region_code":"2270","region_name":"Muscat","country_code":"187","country_name":"Oman"}]},{"region_code":"2271","region_name":"Name Unknown","country_code":"187","country_name":"Oman","cities":[{"city_code":"23613","city_name":"Administrative unit not available","region_code":"2271","region_name":"Name Unknown","country_code":"187","country_name":"Oman"}]}]}