{"country_code":"264","country_name":"Vietnam","country_iso2":"VN","country_iso3":"VNM","regions":[{"region_code":"3326","region_name":"An Giang","country_code":"264","country_name":"Vietnam","cities":[{"city_code":"32174","city_name":"Chau Doc Township","region_code":"3326","region_name":"An Giang","country_code":"264","country_name":"Vietnam"},{"city_code":"32175","city_name":"Chau Phu","region_code":"3326","region_name":"An Giang","country_code":"264","country_name":"Vietnam"},{"city_code":"32176","city_name":"Chau Thanh","region_code":"3326","region_name":"An Giang","country_code":"264","country_name":"Vietnam"},{"city_code":"32177","city_name":"Cho Moi","region_code":"3326","region_name":"An Giang","country_code":"264","country_name":"Vietnam"},{"city_code":"32178","city_name":"Long Xuyen City","region_code":"3326","region_name":"An Giang","country_code":"264","country_name":"Vietnam"},{"city_code":"32179","city_name":"An Phu","region_code":"3326","region_name":"An Giang","country_code":"264","country_name":"Vietnam"},{"city_code":"32180","city_name":"Phu Tan","region_code":"3326","region_name":"An Giang","country_code":"264","country_name":"Vietnam"},{"city_code":"32181","city_name":"Thoai Son","region_code":"3326","region_name":"An Giang","country_code":"264","country_name":"Vietnam"},{"city_code":"32182","city_name":"Tinh Bien","region_code":"3326","region_name":"An Giang","country_code":"264","country_name":"Vietnam"},{"city_code":"32183","city_name":"Tri Ton","region_code":"3326","region_name":"An Giang","country_code":"264","country_name":"Vietnam"},{"city_code":"73940","city_name":"Tan Chau","region_code":"3326","region_name":"An Giang","country_code":"264","country_name":"Vietnam"}]},{"region_code":"3327","region_name":"Ba Ria-Vung Tau","country_code":"264","country_name":"Vietnam","cities":[{"city_code":"32185","city_name":"Con Dao","region_code":"3327","region_name":"Ba Ria-Vung Tau","country_code":"264","country_name":"Vietnam"},{"city_code":"32186","city_name":"Long Dat","region_code":"3327","region_name":"Ba Ria-Vung Tau","country_code":"264","country_name":"Vietnam"},{"city_code":"32187","city_name":"Vung Tau City","region_code":"3327","region_name":"Ba Ria-Vung Tau","country_code":"264","country_name":"Vietnam"},{"city_code":"32188","city_name":"Xuyen Moc","region_code":"3327","region_name":"Ba Ria-Vung Tau","country_code":"264","country_name":"Vietnam"},{"city_code":"73941","city_name":"Ba Ria Township","region_code":"3327","region_name":"Ba Ria-Vung Tau","country_code":"264","country_name":"Vietnam"},{"city_code":"73942","city_name":"Chau Duc","region_code":"3327","region_name":"Ba Ria-Vung Tau","country_code":"264","country_name":"Vietnam"},{"city_code":"73943","city_name":"Tan Thanh","region_code":"3327","region_name":"Ba Ria-Vung Tau","country_code":"264","country_name":"Vietnam"}]},{"region_code":"3328","region_name":"Bac Kan","country_code":"264","country_name":"Vietnam","cities":[{"city_code":"32190","city_name":"Bach Thong","region_code":"3328","region_name":"Bac Kan","country_code":"264","country_name":"Vietnam"},{"city_code":"32191","city_name":"Cho Don","region_code":"3328","region_name":"Bac Kan","country_code":"264","country_name":"Vietnam"},{"city_code":"32192","city_name":"Na Ri","region_code":"3328","region_name":"Bac Kan","country_code":"264","country_name":"Vietnam"},{"city_code":"32193","city_name":"Ngan Son","region_code":"3328","region_name":"Bac Kan","country_code":"264","country_name":"Vietnam"},{"city_code":"73945","city_name":"Ba Be","region_code":"3328","region_name":"Bac Kan","country_code":"264","country_name":"Vietnam"},{"city_code":"73946","city_name":"Bac Kan Township","region_code":"3328","region_name":"Bac Kan","country_code":"264","country_name":"Vietnam"},{"city_code":"73947","city_name":"Cho Moi","region_code":"3328","region_name":"Bac Kan","country_code":"264","country_name":"Vietnam"},{"city_code":"73948","city_name":"Pac Nam","region_code":"3328","region_name":"Bac Kan","country_code":"264","country_name":"Vietnam"}]},{"region_code":"3329","region_name":"Bac Giang","country_code":"264","country_name":"Vietnam","cities":[{"city_code":"32194","city_name":"Bac Giang City","region_code":"3329","region_name":"Bac Giang","country_code":"264","country_name":"Vietnam"},{"city_code":"32195","city_name":"Hiep Hoa","region_code":"3329","region_name":"Bac Giang","country_code":"264","country_name":"Vietnam"},{"city_code":"32196","city_name":"Lang Giang","region_code":"3329","region_name":"Bac Giang","country_code":"264","country_name":"Vietnam"},{"city_code":"32197","city_name":"Luc Nam","region_code":"3329","region_name":"Bac Giang","country_code":"264","country_name":"Vietnam"},{"city_code":"32198","city_name":"Luc Ngan","region_code":"3329","region_name":"Bac Giang","country_code":"264","country_name":"Vietnam"},{"city_code":"32199","city_name":"Son Dong","region_code":"3329","region_name":"Bac Giang","country_code":"264","country_name":"Vietnam"},{"city_code":"32200","city_name":"Tan Yen","region_code":"3329","region_name":"Bac Giang","country_code":"264","country_name":"Vietnam"},{"city_code":"32201","city_name":"Viet Yen","region_code":"3329","region_name":"Bac Giang","country_code":"264","country_name":"Vietnam"},{"city_code":"32202","city_name":"Yen The","region_code":"3329","region_name":"Bac Giang","country_code":"264","country_name":"Vietnam"},{"city_code":"73944","city_name":"Yen Dung","region_code":"3329","region_name":"Bac Giang","country_code":"264","country_name":"Vietnam"}]},{"region_code":"3330","region_name":"Bac Lieu","country_code":"264","country_name":"Vietnam","cities":[{"city_code":"32203","city_name":"Bac Lieu Township","region_code":"3330","region_name":"Bac Lieu","country_code":"264","country_name":"Vietnam"},{"city_code":"32206","city_name":"Vinh Loi","region_code":"3330","region_name":"Bac Lieu","country_code":"264","country_name":"Vietnam"},{"city_code":"73949","city_name":"Dong Hai","region_code":"3330","region_name":"Bac Lieu","country_code":"264","country_name":"Vietnam"},{"city_code":"73950","city_name":"Gia Rai","region_code":"3330","region_name":"Bac Lieu","country_code":"264","country_name":"Vietnam"},{"city_code":"73951","city_name":"Hong Dan","region_code":"3330","region_name":"Bac Lieu","country_code":"264","country_name":"Vietnam"},{"city_code":"73952","city_name":"Phuoc Long","region_code":"3330","region_name":"Bac Lieu","country_code":"264","country_name":"Vietnam"}]},{"region_code":"3331","region_name":"Bac Ninh","country_code":"264","country_name":"Vietnam","cities":[{"city_code":"32208","city_name":"Que Vo","region_code":"3331","region_name":"Bac Ninh","country_code":"264","country_name":"Vietnam"},{"city_code":"32209","city_name":"Thuan Thanh","region_code":"3331","region_name":"Bac Ninh","country_code":"264","country_name":"Vietnam"},{"city_code":"32211","city_name":"Yen Phong","region_code":"3331","region_name":"Bac Ninh","country_code":"264","country_name":"Vietnam"},{"city_code":"73953","city_name":"Bac Ninh Township","region_code":"3331","region_name":"Bac Ninh","country_code":"264","country_name":"Vietnam"},{"city_code":"73954","city_name":"Gia Binh","region_code":"3331","region_name":"Bac Ninh","country_code":"264","country_name":"Vietnam"},{"city_code":"73955","city_name":"Luong Tai","region_code":"3331","region_name":"Bac Ninh","country_code":"264","country_name":"Vietnam"},{"city_code":"73956","city_name":"Tien Du","region_code":"3331","region_name":"Bac Ninh","country_code":"264","country_name":"Vietnam"},{"city_code":"73957","city_name":"Tu Son","region_code":"3331","region_name":"Bac Ninh","country_code":"264","country_name":"Vietnam"}]},{"region_code":"3332","region_name":"Ben Tre","country_code":"264","country_name":"Vietnam","cities":[{"city_code":"32212","city_name":"Ba Tri","region_code":"3332","region_name":"Ben Tre","country_code":"264","country_name":"Vietnam"},{"city_code":"32213","city_name":"Binh Dai","region_code":"3332","region_name":"Ben Tre","country_code":"264","country_name":"Vietnam"},{"city_code":"32214","city_name":"Chau Thanh","region_code":"3332","region_name":"Ben Tre","country_code":"264","country_name":"Vietnam"},{"city_code":"32215","city_name":"Cho Lach","region_code":"3332","region_name":"Ben Tre","country_code":"264","country_name":"Vietnam"},{"city_code":"32216","city_name":"Giong Trom","region_code":"3332","region_name":"Ben Tre","country_code":"264","country_name":"Vietnam"},{"city_code":"32217","city_name":"Mo Cay","region_code":"3332","region_name":"Ben Tre","country_code":"264","country_name":"Vietnam"},{"city_code":"32218","city_name":"Thanh Phu","region_code":"3332","region_name":"Ben Tre","country_code":"264","country_name":"Vietnam"},{"city_code":"73958","city_name":"Ben Tre Township","region_code":"3332","region_name":"Ben Tre","country_code":"264","country_name":"Vietnam"}]},{"region_code":"3333","region_name":"Binh Dinh","country_code":"264","country_name":"Vietnam","cities":[{"city_code":"32220","city_name":"An Lao","region_code":"3333","region_name":"Binh Dinh","country_code":"264","country_name":"Vietnam"},{"city_code":"32221","city_name":"An Nhon","region_code":"3333","region_name":"Binh Dinh","country_code":"264","country_name":"Vietnam"},{"city_code":"32222","city_name":"Hoai an","region_code":"3333","region_name":"Binh Dinh","country_code":"264","country_name":"Vietnam"},{"city_code":"32223","city_name":"Phu Cat","region_code":"3333","region_name":"Binh Dinh","country_code":"264","country_name":"Vietnam"},{"city_code":"32224","city_name":"Phu My","region_code":"3333","region_name":"Binh Dinh","country_code":"264","country_name":"Vietnam"},{"city_code":"32225","city_name":"Qui Nhon City","region_code":"3333","region_name":"Binh Dinh","country_code":"264","country_name":"Vietnam"},{"city_code":"32226","city_name":"Tay Son","region_code":"3333","region_name":"Binh Dinh","country_code":"264","country_name":"Vietnam"},{"city_code":"32227","city_name":"Tuy Phuoc","region_code":"3333","region_name":"Binh Dinh","country_code":"264","country_name":"Vietnam"},{"city_code":"32228","city_name":"Van Canh","region_code":"3333","region_name":"Binh Dinh","country_code":"264","country_name":"Vietnam"},{"city_code":"32229","city_name":"Vinh Thanh","region_code":"3333","region_name":"Binh Dinh","country_code":"264","country_name":"Vietnam"},{"city_code":"73959","city_name":"Hoai Nhon","region_code":"3333","region_name":"Binh Dinh","country_code":"264","country_name":"Vietnam"}]},{"region_code":"3334","region_name":"Binh Duong","country_code":"264","country_name":"Vietnam","cities":[{"city_code":"32230","city_name":"Ben Cat","region_code":"3334","region_name":"Binh Duong","country_code":"264","country_name":"Vietnam"},{"city_code":"32231","city_name":"Tan Uyen","region_code":"3334","region_name":"Binh Duong","country_code":"264","country_name":"Vietnam"},{"city_code":"32232","city_name":"Thu Dau Mot Township","region_code":"3334","region_name":"Binh Duong","country_code":"264","country_name":"Vietnam"},{"city_code":"32233","city_name":"Thuan An","region_code":"3334","region_name":"Binh Duong","country_code":"264","country_name":"Vietnam"},{"city_code":"73960","city_name":"Dau Tieng","region_code":"3334","region_name":"Binh Duong","country_code":"264","country_name":"Vietnam"},{"city_code":"73961","city_name":"Di An","region_code":"3334","region_name":"Binh Duong","country_code":"264","country_name":"Vietnam"},{"city_code":"73962","city_name":"Phu Giao","region_code":"3334","region_name":"Binh Duong","country_code":"264","country_name":"Vietnam"}]},{"region_code":"3335","region_name":"Binh Phuoc","country_code":"264","country_name":"Vietnam","cities":[{"city_code":"32235","city_name":"Bu Dang","region_code":"3335","region_name":"Binh Phuoc","country_code":"264","country_name":"Vietnam"},{"city_code":"32236","city_name":"Dong Phu","region_code":"3335","region_name":"Binh Phuoc","country_code":"264","country_name":"Vietnam"},{"city_code":"32238","city_name":"Phuoc Long","region_code":"3335","region_name":"Binh Phuoc","country_code":"264","country_name":"Vietnam"},{"city_code":"73963","city_name":"Binh Long","region_code":"3335","region_name":"Binh Phuoc","country_code":"264","country_name":"Vietnam"},{"city_code":"73964","city_name":"Bu Dop","region_code":"3335","region_name":"Binh Phuoc","country_code":"264","country_name":"Vietnam"},{"city_code":"73965","city_name":"Chon Thanh","region_code":"3335","region_name":"Binh Phuoc","country_code":"264","country_name":"Vietnam"},{"city_code":"73966","city_name":"Loc Ninh","region_code":"3335","region_name":"Binh Phuoc","country_code":"264","country_name":"Vietnam"},{"city_code":"73967","city_name":"Thi Xa Dong Xoai","region_code":"3335","region_name":"Binh Phuoc","country_code":"264","country_name":"Vietnam"}]},{"region_code":"3336","region_name":"Binh Thuan","country_code":"264","country_name":"Vietnam","cities":[{"city_code":"32239","city_name":"Bac Binh","region_code":"3336","region_name":"Binh Thuan","country_code":"264","country_name":"Vietnam"},{"city_code":"32240","city_name":"Duc Linh","region_code":"3336","region_name":"Binh Thuan","country_code":"264","country_name":"Vietnam"},{"city_code":"32241","city_name":"Ham Tan","region_code":"3336","region_name":"Binh Thuan","country_code":"264","country_name":"Vietnam"},{"city_code":"32242","city_name":"H.Thuan Nam","region_code":"3336","region_name":"Binh Thuan","country_code":"264","country_name":"Vietnam"},{"city_code":"32243","city_name":"HThuan Bac","region_code":"3336","region_name":"Binh Thuan","country_code":"264","country_name":"Vietnam"},{"city_code":"32244","city_name":"Phan Thiet City","region_code":"3336","region_name":"Binh Thuan","country_code":"264","country_name":"Vietnam"},{"city_code":"32245","city_name":"Tanh Linh","region_code":"3336","region_name":"Binh Thuan","country_code":"264","country_name":"Vietnam"},{"city_code":"32246","city_name":"Tuy Phong","region_code":"3336","region_name":"Binh Thuan","country_code":"264","country_name":"Vietnam"}]},{"region_code":"3338","region_name":"Cao Bang","country_code":"264","country_name":"Vietnam","cities":[{"city_code":"32255","city_name":"Ha Lang","region_code":"3338","region_name":"Cao Bang","country_code":"264","country_name":"Vietnam"},{"city_code":"32256","city_name":"Ha Quang","region_code":"3338","region_name":"Cao Bang","country_code":"264","country_name":"Vietnam"},{"city_code":"32257","city_name":"Hoa An","region_code":"3338","region_name":"Cao Bang","country_code":"264","country_name":"Vietnam"},{"city_code":"32258","city_name":"Nguyen Binh","region_code":"3338","region_name":"Cao Bang","country_code":"264","country_name":"Vietnam"},{"city_code":"32260","city_name":"Thong Nong","region_code":"3338","region_name":"Cao Bang","country_code":"264","country_name":"Vietnam"},{"city_code":"32261","city_name":"Tra Linh","region_code":"3338","region_name":"Cao Bang","country_code":"264","country_name":"Vietnam"},{"city_code":"32262","city_name":"Trung Khanh","region_code":"3338","region_name":"Cao Bang","country_code":"264","country_name":"Vietnam"},{"city_code":"73983","city_name":"Bao Lac","region_code":"3338","region_name":"Cao Bang","country_code":"264","country_name":"Vietnam"},{"city_code":"73984","city_name":"Bao Lam","region_code":"3338","region_name":"Cao Bang","country_code":"264","country_name":"Vietnam"},{"city_code":"73985","city_name":"Cao Bang Township","region_code":"3338","region_name":"Cao Bang","country_code":"264","country_name":"Vietnam"},{"city_code":"73986","city_name":"Phuc Hoa","region_code":"3338","region_name":"Cao Bang","country_code":"264","country_name":"Vietnam"},{"city_code":"73987","city_name":"Quang Uyen","region_code":"3338","region_name":"Cao Bang","country_code":"264","country_name":"Vietnam"},{"city_code":"73988","city_name":"Thach An","region_code":"3338","region_name":"Cao Bang","country_code":"264","country_name":"Vietnam"}]},{"region_code":"3339","region_name":"Ca Mau","country_code":"264","country_name":"Vietnam","cities":[{"city_code":"32264","city_name":"Ca Mau City","region_code":"3339","region_name":"Ca Mau","country_code":"264","country_name":"Vietnam"},{"city_code":"32268","city_name":"Tran Van Thoi","region_code":"3339","region_name":"Ca Mau","country_code":"264","country_name":"Vietnam"},{"city_code":"32269","city_name":"U Minh","region_code":"3339","region_name":"Ca Mau","country_code":"264","country_name":"Vietnam"},{"city_code":"73969","city_name":"Cai Nuoc","region_code":"3339","region_name":"Ca Mau","country_code":"264","country_name":"Vietnam"},{"city_code":"73970","city_name":"Dam Doi","region_code":"3339","region_name":"Ca Mau","country_code":"264","country_name":"Vietnam"},{"city_code":"73971","city_name":"Nam Can","region_code":"3339","region_name":"Ca Mau","country_code":"264","country_name":"Vietnam"},{"city_code":"73972","city_name":"Ngoc Hien","region_code":"3339","region_name":"Ca Mau","country_code":"264","country_name":"Vietnam"},{"city_code":"73973","city_name":"Phu Tan","region_code":"3339","region_name":"Ca Mau","country_code":"264","country_name":"Vietnam"},{"city_code":"73974","city_name":"Thoi Binh","region_code":"3339","region_name":"Ca Mau","country_code":"264","country_name":"Vietnam"}]},{"region_code":"3340","region_name":"Da Nang City","country_code":"264","country_name":"Vietnam","cities":[{"city_code":"32272","city_name":"Hoa Vang","region_code":"3340","region_name":"Da Nang City","country_code":"264","country_name":"Vietnam"},{"city_code":"73989","city_name":"Hai Chau","region_code":"3340","region_name":"Da Nang City","country_code":"264","country_name":"Vietnam"},{"city_code":"73990","city_name":"Lien Chieu","region_code":"3340","region_name":"Da Nang City","country_code":"264","country_name":"Vietnam"},{"city_code":"73991","city_name":"Ngu Hanh Son","region_code":"3340","region_name":"Da Nang City","country_code":"264","country_name":"Vietnam"},{"city_code":"73992","city_name":"Son Tra","region_code":"3340","region_name":"Da Nang City","country_code":"264","country_name":"Vietnam"},{"city_code":"73993","city_name":"Thanh Khe","region_code":"3340","region_name":"Da Nang City","country_code":"264","country_name":"Vietnam"}]},{"region_code":"3342","region_name":"Dong Nai","country_code":"264","country_name":"Vietnam","cities":[{"city_code":"32290","city_name":"Bien Hoa City","region_code":"3342","region_name":"Dong Nai","country_code":"264","country_name":"Vietnam"},{"city_code":"32291","city_name":"Long Thanh","region_code":"3342","region_name":"Dong Nai","country_code":"264","country_name":"Vietnam"},{"city_code":"32292","city_name":"Tan Phu","region_code":"3342","region_name":"Dong Nai","country_code":"264","country_name":"Vietnam"},{"city_code":"74032","city_name":"Cam My","region_code":"3342","region_name":"Dong Nai","country_code":"264","country_name":"Vietnam"},{"city_code":"74033","city_name":"Dinh Quan","region_code":"3342","region_name":"Dong Nai","country_code":"264","country_name":"Vietnam"},{"city_code":"74034","city_name":"Long Khanh Township","region_code":"3342","region_name":"Dong Nai","country_code":"264","country_name":"Vietnam"},{"city_code":"74035","city_name":"Nhon Trach","region_code":"3342","region_name":"Dong Nai","country_code":"264","country_name":"Vietnam"},{"city_code":"74036","city_name":"Thong Nhat","region_code":"3342","region_name":"Dong Nai","country_code":"264","country_name":"Vietnam"},{"city_code":"74037","city_name":"Trang Bom","region_code":"3342","region_name":"Dong Nai","country_code":"264","country_name":"Vietnam"},{"city_code":"74038","city_name":"Vinh Cuu","region_code":"3342","region_name":"Dong Nai","country_code":"264","country_name":"Vietnam"},{"city_code":"74039","city_name":"Xuan Loc","region_code":"3342","region_name":"Dong Nai","country_code":"264","country_name":"Vietnam"}]},{"region_code":"3343","region_name":"Dong Thap","country_code":"264","country_name":"Vietnam","cities":[{"city_code":"32296","city_name":"Cao Lanh","region_code":"3343","region_name":"Dong Thap","country_code":"264","country_name":"Vietnam"},{"city_code":"32297","city_name":"Chau Thanh","region_code":"3343","region_name":"Dong Thap","country_code":"264","country_name":"Vietnam"},{"city_code":"32298","city_name":"Hong Ngu","region_code":"3343","region_name":"Dong Thap","country_code":"264","country_name":"Vietnam"},{"city_code":"32299","city_name":"Sa Dec Township","region_code":"3343","region_name":"Dong Thap","country_code":"264","country_name":"Vietnam"},{"city_code":"32300","city_name":"Tam Nong","region_code":"3343","region_name":"Dong Thap","country_code":"264","country_name":"Vietnam"},{"city_code":"32301","city_name":"Thanh Binh","region_code":"3343","region_name":"Dong Thap","country_code":"264","country_name":"Vietnam"},{"city_code":"32303","city_name":"Thap Muoi","region_code":"3343","region_name":"Dong Thap","country_code":"264","country_name":"Vietnam"},{"city_code":"32304","city_name":"Cao Lanh Township","region_code":"3343","region_name":"Dong Thap","country_code":"264","country_name":"Vietnam"},{"city_code":"74040","city_name":"Lai Vung","region_code":"3343","region_name":"Dong Thap","country_code":"264","country_name":"Vietnam"},{"city_code":"74041","city_name":"Lap Vo","region_code":"3343","region_name":"Dong Thap","country_code":"264","country_name":"Vietnam"},{"city_code":"74042","city_name":"Tan Hong","region_code":"3343","region_name":"Dong Thap","country_code":"264","country_name":"Vietnam"}]},{"region_code":"3344","region_name":"Gia Lai","country_code":"264","country_name":"Vietnam","cities":[{"city_code":"32308","city_name":"Chu Se","region_code":"3344","region_name":"Gia Lai","country_code":"264","country_name":"Vietnam"},{"city_code":"32309","city_name":"KBang","region_code":"3344","region_name":"Gia Lai","country_code":"264","country_name":"Vietnam"},{"city_code":"32310","city_name":"Kong Chro","region_code":"3344","region_name":"Gia Lai","country_code":"264","country_name":"Vietnam"},{"city_code":"32311","city_name":"Krong Pa","region_code":"3344","region_name":"Gia Lai","country_code":"264","country_name":"Vietnam"},{"city_code":"32313","city_name":"Pleiku Township","region_code":"3344","region_name":"Gia Lai","country_code":"264","country_name":"Vietnam"},{"city_code":"74043","city_name":"An Khe township","region_code":"3344","region_name":"Gia Lai","country_code":"264","country_name":"Vietnam"},{"city_code":"74044","city_name":"Ayun Pa","region_code":"3344","region_name":"Gia Lai","country_code":"264","country_name":"Vietnam"},{"city_code":"74045","city_name":"Chu Pah","region_code":"3344","region_name":"Gia Lai","country_code":"264","country_name":"Vietnam"},{"city_code":"74046","city_name":"Chu Prong","region_code":"3344","region_name":"Gia Lai","country_code":"264","country_name":"Vietnam"},{"city_code":"74047","city_name":"Dak Doa","region_code":"3344","region_name":"Gia Lai","country_code":"264","country_name":"Vietnam"},{"city_code":"74048","city_name":"Dak Po","region_code":"3344","region_name":"Gia Lai","country_code":"264","country_name":"Vietnam"},{"city_code":"74049","city_name":"Duc Co","region_code":"3344","region_name":"Gia Lai","country_code":"264","country_name":"Vietnam"},{"city_code":"74050","city_name":"Ia Grai","region_code":"3344","region_name":"Gia Lai","country_code":"264","country_name":"Vietnam"},{"city_code":"74051","city_name":"Ia Pa","region_code":"3344","region_name":"Gia Lai","country_code":"264","country_name":"Vietnam"},{"city_code":"74052","city_name":"Mang Yang","region_code":"3344","region_name":"Gia Lai","country_code":"264","country_name":"Vietnam"}]},{"region_code":"3345","region_name":"Ha Giang","country_code":"264","country_name":"Vietnam","cities":[{"city_code":"32314","city_name":"Bac Me","region_code":"3345","region_name":"Ha Giang","country_code":"264","country_name":"Vietnam"},{"city_code":"32316","city_name":"Dong Van","region_code":"3345","region_name":"Ha Giang","country_code":"264","country_name":"Vietnam"},{"city_code":"32318","city_name":"Meo Vac","region_code":"3345","region_name":"Ha Giang","country_code":"264","country_name":"Vietnam"},{"city_code":"32319","city_name":"Quan Ba","region_code":"3345","region_name":"Ha Giang","country_code":"264","country_name":"Vietnam"},{"city_code":"32321","city_name":"Vi Xuyen","region_code":"3345","region_name":"Ha Giang","country_code":"264","country_name":"Vietnam"},{"city_code":"32323","city_name":"Yen Minh","region_code":"3345","region_name":"Ha Giang","country_code":"264","country_name":"Vietnam"},{"city_code":"74053","city_name":"Bac Quang","region_code":"3345","region_name":"Ha Giang","country_code":"264","country_name":"Vietnam"},{"city_code":"74054","city_name":"Ha Giang Township","region_code":"3345","region_name":"Ha Giang","country_code":"264","country_name":"Vietnam"},{"city_code":"74055","city_name":"Hoang Su Phi","region_code":"3345","region_name":"Ha Giang","country_code":"264","country_name":"Vietnam"},{"city_code":"74056","city_name":"Quang Binh","region_code":"3345","region_name":"Ha Giang","country_code":"264","country_name":"Vietnam"},{"city_code":"74057","city_name":"Xin Man","region_code":"3345","region_name":"Ha Giang","country_code":"264","country_name":"Vietnam"}]},{"region_code":"3346","region_name":"Ha Nam","country_code":"264","country_name":"Vietnam","cities":[{"city_code":"32324","city_name":"Binh Luc","region_code":"3346","region_name":"Ha Nam","country_code":"264","country_name":"Vietnam"},{"city_code":"32325","city_name":"Duy Tien","region_code":"3346","region_name":"Ha Nam","country_code":"264","country_name":"Vietnam"},{"city_code":"32327","city_name":"Kim Bang","region_code":"3346","region_name":"Ha Nam","country_code":"264","country_name":"Vietnam"},{"city_code":"32328","city_name":"Thanh Lien","region_code":"3346","region_name":"Ha Nam","country_code":"264","country_name":"Vietnam"},{"city_code":"74058","city_name":"Ly Nhan","region_code":"3346","region_name":"Ha Nam","country_code":"264","country_name":"Vietnam"},{"city_code":"74059","city_name":"Phu Ly Township","region_code":"3346","region_name":"Ha Nam","country_code":"264","country_name":"Vietnam"}]},{"region_code":"3347","region_name":"Ha Noi City","country_code":"264","country_name":"Vietnam","cities":[{"city_code":"32329","city_name":"Dong Anh","region_code":"3347","region_name":"Ha Noi City","country_code":"264","country_name":"Vietnam"},{"city_code":"32332","city_name":"Soc Son","region_code":"3347","region_name":"Ha Noi City","country_code":"264","country_name":"Vietnam"},{"city_code":"74060","city_name":"Ba Dinh","region_code":"3347","region_name":"Ha Noi City","country_code":"264","country_name":"Vietnam"},{"city_code":"74061","city_name":"Cau Giay","region_code":"3347","region_name":"Ha Noi City","country_code":"264","country_name":"Vietnam"},{"city_code":"74062","city_name":"Dong Da","region_code":"3347","region_name":"Ha Noi City","country_code":"264","country_name":"Vietnam"},{"city_code":"74063","city_name":"Gia Lam","region_code":"3347","region_name":"Ha Noi City","country_code":"264","country_name":"Vietnam"},{"city_code":"74064","city_name":"Hai Ba Trung","region_code":"3347","region_name":"Ha Noi City","country_code":"264","country_name":"Vietnam"},{"city_code":"74065","city_name":"Hoan Kiem","region_code":"3347","region_name":"Ha Noi City","country_code":"264","country_name":"Vietnam"},{"city_code":"74066","city_name":"Hoang Mai","region_code":"3347","region_name":"Ha Noi City","country_code":"264","country_name":"Vietnam"},{"city_code":"74067","city_name":"Long Bien","region_code":"3347","region_name":"Ha Noi City","country_code":"264","country_name":"Vietnam"},{"city_code":"74068","city_name":"Tay Ho","region_code":"3347","region_name":"Ha Noi City","country_code":"264","country_name":"Vietnam"},{"city_code":"74069","city_name":"Thanh Tri","region_code":"3347","region_name":"Ha Noi City","country_code":"264","country_name":"Vietnam"},{"city_code":"74070","city_name":"Thanh Xuan","region_code":"3347","region_name":"Ha Noi City","country_code":"264","country_name":"Vietnam"},{"city_code":"74071","city_name":"Tu Lien","region_code":"3347","region_name":"Ha Noi City","country_code":"264","country_name":"Vietnam"}]},{"region_code":"3348","region_name":"Ha Tay","country_code":"264","country_name":"Vietnam","cities":[{"city_code":"32335","city_name":"Ba Vi","region_code":"3348","region_name":"Ha Tay","country_code":"264","country_name":"Vietnam"},{"city_code":"32336","city_name":"Chuong My","region_code":"3348","region_name":"Ha Tay","country_code":"264","country_name":"Vietnam"},{"city_code":"32337","city_name":"Ha Dong Township","region_code":"3348","region_name":"Ha Tay","country_code":"264","country_name":"Vietnam"},{"city_code":"32338","city_name":"Hoai Duc","region_code":"3348","region_name":"Ha Tay","country_code":"264","country_name":"Vietnam"},{"city_code":"32339","city_name":"My Duc","region_code":"3348","region_name":"Ha Tay","country_code":"264","country_name":"Vietnam"},{"city_code":"32340","city_name":"Phu Xuyen","region_code":"3348","region_name":"Ha Tay","country_code":"264","country_name":"Vietnam"},{"city_code":"32341","city_name":"Quoc Oai","region_code":"3348","region_name":"Ha Tay","country_code":"264","country_name":"Vietnam"},{"city_code":"32342","city_name":"Thach That","region_code":"3348","region_name":"Ha Tay","country_code":"264","country_name":"Vietnam"},{"city_code":"32343","city_name":"Thanh Oai","region_code":"3348","region_name":"Ha Tay","country_code":"264","country_name":"Vietnam"},{"city_code":"32344","city_name":"Thuong Tin","region_code":"3348","region_name":"Ha Tay","country_code":"264","country_name":"Vietnam"},{"city_code":"32345","city_name":"Ung Hoa","region_code":"3348","region_name":"Ha Tay","country_code":"264","country_name":"Vietnam"},{"city_code":"74072","city_name":"Dan Phuong","region_code":"3348","region_name":"Ha Tay","country_code":"264","country_name":"Vietnam"},{"city_code":"74073","city_name":"Phuc Tho","region_code":"3348","region_name":"Ha Tay","country_code":"264","country_name":"Vietnam"},{"city_code":"74074","city_name":"Son Tay Township","region_code":"3348","region_name":"Ha Tay","country_code":"264","country_name":"Vietnam"}]},{"region_code":"3349","region_name":"Ha Tinh","country_code":"264","country_name":"Vietnam","cities":[{"city_code":"32346","city_name":"Cam Xuyen","region_code":"3349","region_name":"Ha Tinh","country_code":"264","country_name":"Vietnam"},{"city_code":"32347","city_name":"Can Loc","region_code":"3349","region_name":"Ha Tinh","country_code":"264","country_name":"Vietnam"},{"city_code":"32351","city_name":"Ky Anh","region_code":"3349","region_name":"Ha Tinh","country_code":"264","country_name":"Vietnam"},{"city_code":"32352","city_name":"Nghi Xuan","region_code":"3349","region_name":"Ha Tinh","country_code":"264","country_name":"Vietnam"},{"city_code":"32353","city_name":"Thach Ha","region_code":"3349","region_name":"Ha Tinh","country_code":"264","country_name":"Vietnam"},{"city_code":"74075","city_name":"Duc Tho","region_code":"3349","region_name":"Ha Tinh","country_code":"264","country_name":"Vietnam"},{"city_code":"74076","city_name":"Ha Tinh Township","region_code":"3349","region_name":"Ha Tinh","country_code":"264","country_name":"Vietnam"},{"city_code":"74077","city_name":"Hong Linh Township","region_code":"3349","region_name":"Ha Tinh","country_code":"264","country_name":"Vietnam"},{"city_code":"74078","city_name":"Huong Khe","region_code":"3349","region_name":"Ha Tinh","country_code":"264","country_name":"Vietnam"},{"city_code":"74079","city_name":"Huong Son","region_code":"3349","region_name":"Ha Tinh","country_code":"264","country_name":"Vietnam"},{"city_code":"74080","city_name":"Vu Quang","region_code":"3349","region_name":"Ha Tinh","country_code":"264","country_name":"Vietnam"}]},{"region_code":"3350","region_name":"Hai Duong","country_code":"264","country_name":"Vietnam","cities":[{"city_code":"32355","city_name":"Chi Linh","region_code":"3350","region_name":"Hai Duong","country_code":"264","country_name":"Vietnam"},{"city_code":"74081","city_name":"Binh Giang","region_code":"3350","region_name":"Hai Duong","country_code":"264","country_name":"Vietnam"},{"city_code":"74082","city_name":"Cam Giang","region_code":"3350","region_name":"Hai Duong","country_code":"264","country_name":"Vietnam"},{"city_code":"74083","city_name":"Gia Loc","region_code":"3350","region_name":"Hai Duong","country_code":"264","country_name":"Vietnam"},{"city_code":"74084","city_name":"Hai Duong City","region_code":"3350","region_name":"Hai Duong","country_code":"264","country_name":"Vietnam"},{"city_code":"74085","city_name":"Kim Thanh","region_code":"3350","region_name":"Hai Duong","country_code":"264","country_name":"Vietnam"},{"city_code":"74086","city_name":"Kinh Mon","region_code":"3350","region_name":"Hai Duong","country_code":"264","country_name":"Vietnam"},{"city_code":"74087","city_name":"Nam Sach","region_code":"3350","region_name":"Hai Duong","country_code":"264","country_name":"Vietnam"},{"city_code":"74088","city_name":"Ninh Giang","region_code":"3350","region_name":"Hai Duong","country_code":"264","country_name":"Vietnam"},{"city_code":"74089","city_name":"Thanh Ha","region_code":"3350","region_name":"Hai Duong","country_code":"264","country_name":"Vietnam"},{"city_code":"74090","city_name":"Thanh Mien","region_code":"3350","region_name":"Hai Duong","country_code":"264","country_name":"Vietnam"},{"city_code":"74091","city_name":"Tu Ky","region_code":"3350","region_name":"Hai Duong","country_code":"264","country_name":"Vietnam"}]},{"region_code":"3351","region_name":"Hai Phong City","country_code":"264","country_name":"Vietnam","cities":[{"city_code":"32360","city_name":"An Hai","region_code":"3351","region_name":"Hai Phong City","country_code":"264","country_name":"Vietnam"},{"city_code":"32361","city_name":"An Lao","region_code":"3351","region_name":"Hai Phong City","country_code":"264","country_name":"Vietnam"},{"city_code":"32362","city_name":"Cat Hai","region_code":"3351","region_name":"Hai Phong City","country_code":"264","country_name":"Vietnam"},{"city_code":"32363","city_name":"Do Son Township","region_code":"3351","region_name":"Hai Phong City","country_code":"264","country_name":"Vietnam"},{"city_code":"32365","city_name":"Kien An","region_code":"3351","region_name":"Hai Phong City","country_code":"264","country_name":"Vietnam"},{"city_code":"32366","city_name":"Thuy Nguyen Ward","region_code":"3351","region_name":"Hai Phong City","country_code":"264","country_name":"Vietnam"},{"city_code":"32367","city_name":"Tien Lang","region_code":"3351","region_name":"Hai Phong City","country_code":"264","country_name":"Vietnam"},{"city_code":"32368","city_name":"Vinh Bao","region_code":"3351","region_name":"Hai Phong City","country_code":"264","country_name":"Vietnam"},{"city_code":"74092","city_name":"Hong Bang","region_code":"3351","region_name":"Hai Phong City","country_code":"264","country_name":"Vietnam"},{"city_code":"74093","city_name":"Kien Thuy","region_code":"3351","region_name":"Hai Phong City","country_code":"264","country_name":"Vietnam"},{"city_code":"74094","city_name":"Le Chan","region_code":"3351","region_name":"Hai Phong City","country_code":"264","country_name":"Vietnam"},{"city_code":"74095","city_name":"Ngo Quyen","region_code":"3351","region_name":"Hai Phong City","country_code":"264","country_name":"Vietnam"},{"city_code":"74583","city_name":"Bach Long Vi","region_code":"3351","region_name":"Hai Phong City","country_code":"264","country_name":"Vietnam"}]},{"region_code":"3352","region_name":"Ho Chi Minh City","country_code":"264","country_name":"Vietnam","cities":[{"city_code":"32369","city_name":"Can Gio","region_code":"3352","region_name":"Ho Chi Minh City","country_code":"264","country_name":"Vietnam"},{"city_code":"32636","city_name":"Cu Chi","region_code":"3352","region_name":"Ho Chi Minh City","country_code":"264","country_name":"Vietnam"},{"city_code":"32638","city_name":"Hoc Mon","region_code":"3352","region_name":"Ho Chi Minh City","country_code":"264","country_name":"Vietnam"},{"city_code":"32640","city_name":"Nha Be","region_code":"3352","region_name":"Ho Chi Minh City","country_code":"264","country_name":"Vietnam"},{"city_code":"32641","city_name":"Thu Duc","region_code":"3352","region_name":"Ho Chi Minh City","country_code":"264","country_name":"Vietnam"},{"city_code":"74101","city_name":"Binh Chanh","region_code":"3352","region_name":"Ho Chi Minh City","country_code":"264","country_name":"Vietnam"},{"city_code":"74102","city_name":"Binh Tan","region_code":"3352","region_name":"Ho Chi Minh City","country_code":"264","country_name":"Vietnam"},{"city_code":"74103","city_name":"Binh Thanh","region_code":"3352","region_name":"Ho Chi Minh City","country_code":"264","country_name":"Vietnam"},{"city_code":"74104","city_name":"District 1","region_code":"3352","region_name":"Ho Chi Minh City","country_code":"264","country_name":"Vietnam"},{"city_code":"74105","city_name":"District 10","region_code":"3352","region_name":"Ho Chi Minh City","country_code":"264","country_name":"Vietnam"},{"city_code":"74106","city_name":"District 11","region_code":"3352","region_name":"Ho Chi Minh City","country_code":"264","country_name":"Vietnam"},{"city_code":"74107","city_name":"District 12","region_code":"3352","region_name":"Ho Chi Minh City","country_code":"264","country_name":"Vietnam"},{"city_code":"74108","city_name":"District 2","region_code":"3352","region_name":"Ho Chi Minh City","country_code":"264","country_name":"Vietnam"},{"city_code":"74109","city_name":"District 3","region_code":"3352","region_name":"Ho Chi Minh City","country_code":"264","country_name":"Vietnam"},{"city_code":"74110","city_name":"District 4","region_code":"3352","region_name":"Ho Chi Minh City","country_code":"264","country_name":"Vietnam"},{"city_code":"74111","city_name":"District 5","region_code":"3352","region_name":"Ho Chi Minh City","country_code":"264","country_name":"Vietnam"},{"city_code":"74112","city_name":"District 6","region_code":"3352","region_name":"Ho Chi Minh City","country_code":"264","country_name":"Vietnam"},{"city_code":"74113","city_name":"District 7","region_code":"3352","region_name":"Ho Chi Minh City","country_code":"264","country_name":"Vietnam"},{"city_code":"74114","city_name":"District 8","region_code":"3352","region_name":"Ho Chi Minh City","country_code":"264","country_name":"Vietnam"},{"city_code":"74115","city_name":"District 9","region_code":"3352","region_name":"Ho Chi Minh City","country_code":"264","country_name":"Vietnam"},{"city_code":"74116","city_name":"Go Vap","region_code":"3352","region_name":"Ho Chi Minh City","country_code":"264","country_name":"Vietnam"},{"city_code":"74117","city_name":"Phu Nhuan","region_code":"3352","region_name":"Ho Chi Minh City","country_code":"264","country_name":"Vietnam"},{"city_code":"74118","city_name":"Tan Binh","region_code":"3352","region_name":"Ho Chi Minh City","country_code":"264","country_name":"Vietnam"},{"city_code":"74119","city_name":"Tan Phu","region_code":"3352","region_name":"Ho Chi Minh City","country_code":"264","country_name":"Vietnam"}]},{"region_code":"3353","region_name":"Hoa Binh","country_code":"264","country_name":"Vietnam","cities":[{"city_code":"32370","city_name":"Da Bac","region_code":"3353","region_name":"Hoa Binh","country_code":"264","country_name":"Vietnam"},{"city_code":"32371","city_name":"Kim Boi","region_code":"3353","region_name":"Hoa Binh","country_code":"264","country_name":"Vietnam"},{"city_code":"32373","city_name":"Lac Son","region_code":"3353","region_name":"Hoa Binh","country_code":"264","country_name":"Vietnam"},{"city_code":"32374","city_name":"Lac Thuy","region_code":"3353","region_name":"Hoa Binh","country_code":"264","country_name":"Vietnam"},{"city_code":"32375","city_name":"Luong Son","region_code":"3353","region_name":"Hoa Binh","country_code":"264","country_name":"Vietnam"},{"city_code":"32376","city_name":"Mai Chau","region_code":"3353","region_name":"Hoa Binh","country_code":"264","country_name":"Vietnam"},{"city_code":"32377","city_name":"Tan Lac","region_code":"3353","region_name":"Hoa Binh","country_code":"264","country_name":"Vietnam"},{"city_code":"32379","city_name":"Yen Thuy","region_code":"3353","region_name":"Hoa Binh","country_code":"264","country_name":"Vietnam"},{"city_code":"74120","city_name":"Cao Phong","region_code":"3353","region_name":"Hoa Binh","country_code":"264","country_name":"Vietnam"},{"city_code":"74121","city_name":"Hoa Binh Township","region_code":"3353","region_name":"Hoa Binh","country_code":"264","country_name":"Vietnam"},{"city_code":"74122","city_name":"Ky Son","region_code":"3353","region_name":"Hoa Binh","country_code":"264","country_name":"Vietnam"}]},{"region_code":"3354","region_name":"Hung Yen","country_code":"264","country_name":"Vietnam","cities":[{"city_code":"32381","city_name":"Hung Yen Township","region_code":"3354","region_name":"Hung Yen","country_code":"264","country_name":"Vietnam"},{"city_code":"74123","city_name":"An Thi","region_code":"3354","region_name":"Hung Yen","country_code":"264","country_name":"Vietnam"},{"city_code":"74124","city_name":"Khoai Chau","region_code":"3354","region_name":"Hung Yen","country_code":"264","country_name":"Vietnam"},{"city_code":"74125","city_name":"Kim Dong","region_code":"3354","region_name":"Hung Yen","country_code":"264","country_name":"Vietnam"},{"city_code":"74126","city_name":"My Hao","region_code":"3354","region_name":"Hung Yen","country_code":"264","country_name":"Vietnam"},{"city_code":"74127","city_name":"Phu Cu","region_code":"3354","region_name":"Hung Yen","country_code":"264","country_name":"Vietnam"},{"city_code":"74128","city_name":"Tien Lu","region_code":"3354","region_name":"Hung Yen","country_code":"264","country_name":"Vietnam"},{"city_code":"74129","city_name":"Van Giang","region_code":"3354","region_name":"Hung Yen","country_code":"264","country_name":"Vietnam"},{"city_code":"74130","city_name":"Van Lam","region_code":"3354","region_name":"Hung Yen","country_code":"264","country_name":"Vietnam"},{"city_code":"74131","city_name":"Yen My","region_code":"3354","region_name":"Hung Yen","country_code":"264","country_name":"Vietnam"}]},{"region_code":"3355","region_name":"Khanh Hoa","country_code":"264","country_name":"Vietnam","cities":[{"city_code":"32386","city_name":"Cam Ranh Township","region_code":"3355","region_name":"Khanh Hoa","country_code":"264","country_name":"Vietnam"},{"city_code":"32387","city_name":"Dien Khanh","region_code":"3355","region_name":"Khanh Hoa","country_code":"264","country_name":"Vietnam"},{"city_code":"32388","city_name":"Khanh Son","region_code":"3355","region_name":"Khanh Hoa","country_code":"264","country_name":"Vietnam"},{"city_code":"32389","city_name":"Khanh Vinh","region_code":"3355","region_name":"Khanh Hoa","country_code":"264","country_name":"Vietnam"},{"city_code":"32391","city_name":"Ninh Hoa","region_code":"3355","region_name":"Khanh Hoa","country_code":"264","country_name":"Vietnam"},{"city_code":"32392","city_name":"Van Ninh","region_code":"3355","region_name":"Khanh Hoa","country_code":"264","country_name":"Vietnam"},{"city_code":"74132","city_name":"Nha Trang City","region_code":"3355","region_name":"Khanh Hoa","country_code":"264","country_name":"Vietnam"}]},{"region_code":"3356","region_name":"Kien Giang","country_code":"264","country_name":"Vietnam","cities":[{"city_code":"32393","city_name":"An Bien","region_code":"3356","region_name":"Kien Giang","country_code":"264","country_name":"Vietnam"},{"city_code":"32394","city_name":"An Minh","region_code":"3356","region_name":"Kien Giang","country_code":"264","country_name":"Vietnam"},{"city_code":"32395","city_name":"Chau Thanh","region_code":"3356","region_name":"Kien Giang","country_code":"264","country_name":"Vietnam"},{"city_code":"32397","city_name":"Go Quao","region_code":"3356","region_name":"Kien Giang","country_code":"264","country_name":"Vietnam"},{"city_code":"32399","city_name":"Hon Dat","region_code":"3356","region_name":"Kien Giang","country_code":"264","country_name":"Vietnam"},{"city_code":"32401","city_name":"Phu Quoc","region_code":"3356","region_name":"Kien Giang","country_code":"264","country_name":"Vietnam"},{"city_code":"32402","city_name":"Rach Gia Township","region_code":"3356","region_name":"Kien Giang","country_code":"264","country_name":"Vietnam"},{"city_code":"32403","city_name":"Tan Hiep","region_code":"3356","region_name":"Kien Giang","country_code":"264","country_name":"Vietnam"},{"city_code":"32405","city_name":"Vinh Thuan","region_code":"3356","region_name":"Kien Giang","country_code":"264","country_name":"Vietnam"},{"city_code":"74133","city_name":"Giong Gieng","region_code":"3356","region_name":"Kien Giang","country_code":"264","country_name":"Vietnam"},{"city_code":"74246","city_name":"Ha Tien Township","region_code":"3356","region_name":"Kien Giang","country_code":"264","country_name":"Vietnam"},{"city_code":"74317","city_name":"Kien Luong","region_code":"3356","region_name":"Kien Giang","country_code":"264","country_name":"Vietnam"},{"city_code":"74318","city_name":"Kien Hai","region_code":"3356","region_name":"Kien Giang","country_code":"264","country_name":"Vietnam"}]},{"region_code":"3357","region_name":"Kon Tum","country_code":"264","country_name":"Vietnam","cities":[{"city_code":"32408","city_name":"Kon Tum Township","region_code":"3357","region_name":"Kon Tum","country_code":"264","country_name":"Vietnam"},{"city_code":"32410","city_name":"Sa Thay","region_code":"3357","region_name":"Kon Tum","country_code":"264","country_name":"Vietnam"},{"city_code":"74134","city_name":"Dak Glei","region_code":"3357","region_name":"Kon Tum","country_code":"264","country_name":"Vietnam"},{"city_code":"74135","city_name":"Dak Ha","region_code":"3357","region_name":"Kon Tum","country_code":"264","country_name":"Vietnam"},{"city_code":"74136","city_name":"Dak To","region_code":"3357","region_name":"Kon Tum","country_code":"264","country_name":"Vietnam"},{"city_code":"74137","city_name":"Kon Plong","region_code":"3357","region_name":"Kon Tum","country_code":"264","country_name":"Vietnam"},{"city_code":"74138","city_name":"Kon Ray","region_code":"3357","region_name":"Kon Tum","country_code":"264","country_name":"Vietnam"},{"city_code":"74139","city_name":"Ngoc Hoi","region_code":"3357","region_name":"Kon Tum","country_code":"264","country_name":"Vietnam"}]},{"region_code":"3359","region_name":"Lam Dong","country_code":"264","country_name":"Vietnam","cities":[{"city_code":"32419","city_name":"Bao Loc Township","region_code":"3359","region_name":"Lam Dong","country_code":"264","country_name":"Vietnam"},{"city_code":"32420","city_name":"Cat Tien","region_code":"3359","region_name":"Lam Dong","country_code":"264","country_name":"Vietnam"},{"city_code":"32422","city_name":"Da Teh","region_code":"3359","region_name":"Lam Dong","country_code":"264","country_name":"Vietnam"},{"city_code":"32424","city_name":"Di Linh","region_code":"3359","region_name":"Lam Dong","country_code":"264","country_name":"Vietnam"},{"city_code":"32425","city_name":"Don Duong","region_code":"3359","region_name":"Lam Dong","country_code":"264","country_name":"Vietnam"},{"city_code":"32426","city_name":"Duc Trong","region_code":"3359","region_name":"Lam Dong","country_code":"264","country_name":"Vietnam"},{"city_code":"32427","city_name":"Lac Duong","region_code":"3359","region_name":"Lam Dong","country_code":"264","country_name":"Vietnam"},{"city_code":"32428","city_name":"Lam Ha","region_code":"3359","region_name":"Lam Dong","country_code":"264","country_name":"Vietnam"},{"city_code":"74146","city_name":"Bao Lam","region_code":"3359","region_name":"Lam Dong","country_code":"264","country_name":"Vietnam"},{"city_code":"74147","city_name":"Da Huoai","region_code":"3359","region_name":"Lam Dong","country_code":"264","country_name":"Vietnam"},{"city_code":"74148","city_name":"Da Lat City","region_code":"3359","region_name":"Lam Dong","country_code":"264","country_name":"Vietnam"}]},{"region_code":"3360","region_name":"Lang Son","country_code":"264","country_name":"Vietnam","cities":[{"city_code":"32429","city_name":"Bac Son","region_code":"3360","region_name":"Lang Son","country_code":"264","country_name":"Vietnam"},{"city_code":"32430","city_name":"Binh Gia","region_code":"3360","region_name":"Lang Son","country_code":"264","country_name":"Vietnam"},{"city_code":"32431","city_name":"Cao Loc","region_code":"3360","region_name":"Lang Son","country_code":"264","country_name":"Vietnam"},{"city_code":"32432","city_name":"Chi Lang","region_code":"3360","region_name":"Lang Son","country_code":"264","country_name":"Vietnam"},{"city_code":"32433","city_name":"Dinh Lap","region_code":"3360","region_name":"Lang Son","country_code":"264","country_name":"Vietnam"},{"city_code":"32434","city_name":"Huu Lung","region_code":"3360","region_name":"Lang Son","country_code":"264","country_name":"Vietnam"},{"city_code":"32435","city_name":"Loc Binh","region_code":"3360","region_name":"Lang Son","country_code":"264","country_name":"Vietnam"},{"city_code":"32436","city_name":"Trang Dinh","region_code":"3360","region_name":"Lang Son","country_code":"264","country_name":"Vietnam"},{"city_code":"32438","city_name":"Van Lang","region_code":"3360","region_name":"Lang Son","country_code":"264","country_name":"Vietnam"},{"city_code":"32439","city_name":"Van Quan","region_code":"3360","region_name":"Lang Son","country_code":"264","country_name":"Vietnam"},{"city_code":"74149","city_name":"Lang Son City","region_code":"3360","region_name":"Lang Son","country_code":"264","country_name":"Vietnam"}]},{"region_code":"3362","region_name":"Long An","country_code":"264","country_name":"Vietnam","cities":[{"city_code":"32448","city_name":"Ben Luc","region_code":"3362","region_name":"Long An","country_code":"264","country_name":"Vietnam"},{"city_code":"32449","city_name":"Can Duoc","region_code":"3362","region_name":"Long An","country_code":"264","country_name":"Vietnam"},{"city_code":"32450","city_name":"Can Giuoc","region_code":"3362","region_name":"Long An","country_code":"264","country_name":"Vietnam"},{"city_code":"32451","city_name":"Chau Thanh","region_code":"3362","region_name":"Long An","country_code":"264","country_name":"Vietnam"},{"city_code":"32452","city_name":"Duc Hoa","region_code":"3362","region_name":"Long An","country_code":"264","country_name":"Vietnam"},{"city_code":"32453","city_name":"Duc Hue","region_code":"3362","region_name":"Long An","country_code":"264","country_name":"Vietnam"},{"city_code":"32454","city_name":"Moc Hoa","region_code":"3362","region_name":"Long An","country_code":"264","country_name":"Vietnam"},{"city_code":"32455","city_name":"Tan Thanh","region_code":"3362","region_name":"Long An","country_code":"264","country_name":"Vietnam"},{"city_code":"32456","city_name":"Tan Tru","region_code":"3362","region_name":"Long An","country_code":"264","country_name":"Vietnam"},{"city_code":"32457","city_name":"Thanh Hoa","region_code":"3362","region_name":"Long An","country_code":"264","country_name":"Vietnam"},{"city_code":"32458","city_name":"Vinh Hung","region_code":"3362","region_name":"Long An","country_code":"264","country_name":"Vietnam"},{"city_code":"74154","city_name":"Tan An Township","region_code":"3362","region_name":"Long An","country_code":"264","country_name":"Vietnam"},{"city_code":"74155","city_name":"Tan Hung","region_code":"3362","region_name":"Long An","country_code":"264","country_name":"Vietnam"},{"city_code":"74156","city_name":"Thu Thua","region_code":"3362","region_name":"Long An","country_code":"264","country_name":"Vietnam"}]},{"region_code":"3364","region_name":"Nam Dinh","country_code":"264","country_name":"Vietnam","cities":[{"city_code":"32461","city_name":"Hai Hau","region_code":"3364","region_name":"Nam Dinh","country_code":"264","country_name":"Vietnam"},{"city_code":"32462","city_name":"Nam Dinh City","region_code":"3364","region_name":"Nam Dinh","country_code":"264","country_name":"Vietnam"},{"city_code":"32464","city_name":"Nghia Hung","region_code":"3364","region_name":"Nam Dinh","country_code":"264","country_name":"Vietnam"},{"city_code":"32465","city_name":"Vu Ban","region_code":"3364","region_name":"Nam Dinh","country_code":"264","country_name":"Vietnam"},{"city_code":"32467","city_name":"Y Yen","region_code":"3364","region_name":"Nam Dinh","country_code":"264","country_name":"Vietnam"},{"city_code":"74157","city_name":"Giao Thuy","region_code":"3364","region_name":"Nam Dinh","country_code":"264","country_name":"Vietnam"},{"city_code":"74158","city_name":"My Loc","region_code":"3364","region_name":"Nam Dinh","country_code":"264","country_name":"Vietnam"},{"city_code":"74159","city_name":"Nam Truc","region_code":"3364","region_name":"Nam Dinh","country_code":"264","country_name":"Vietnam"},{"city_code":"74160","city_name":"Truc Ninh","region_code":"3364","region_name":"Nam Dinh","country_code":"264","country_name":"Vietnam"},{"city_code":"74161","city_name":"Xuan Truong","region_code":"3364","region_name":"Nam Dinh","country_code":"264","country_name":"Vietnam"}]},{"region_code":"3366","region_name":"Nghe An","country_code":"264","country_name":"Vietnam","cities":[{"city_code":"32469","city_name":"Anh Son","region_code":"3366","region_name":"Nghe An","country_code":"264","country_name":"Vietnam"},{"city_code":"32470","city_name":"Con Cuong","region_code":"3366","region_name":"Nghe An","country_code":"264","country_name":"Vietnam"},{"city_code":"32471","city_name":"Dien Chau","region_code":"3366","region_name":"Nghe An","country_code":"264","country_name":"Vietnam"},{"city_code":"32472","city_name":"Do Luong","region_code":"3366","region_name":"Nghe An","country_code":"264","country_name":"Vietnam"},{"city_code":"32473","city_name":"Hung Nguyen","region_code":"3366","region_name":"Nghe An","country_code":"264","country_name":"Vietnam"},{"city_code":"32474","city_name":"Ky Son","region_code":"3366","region_name":"Nghe An","country_code":"264","country_name":"Vietnam"},{"city_code":"32475","city_name":"Nam Dan","region_code":"3366","region_name":"Nghe An","country_code":"264","country_name":"Vietnam"},{"city_code":"32476","city_name":"Nghi Loc","region_code":"3366","region_name":"Nghe An","country_code":"264","country_name":"Vietnam"},{"city_code":"32477","city_name":"Nghia Dan","region_code":"3366","region_name":"Nghe An","country_code":"264","country_name":"Vietnam"},{"city_code":"32478","city_name":"Que Phong","region_code":"3366","region_name":"Nghe An","country_code":"264","country_name":"Vietnam"},{"city_code":"32479","city_name":"Quy Chau","region_code":"3366","region_name":"Nghe An","country_code":"264","country_name":"Vietnam"},{"city_code":"32480","city_name":"Quy Hop","region_code":"3366","region_name":"Nghe An","country_code":"264","country_name":"Vietnam"},{"city_code":"32481","city_name":"Quynh Luu","region_code":"3366","region_name":"Nghe An","country_code":"264","country_name":"Vietnam"},{"city_code":"32482","city_name":"Tan Ky","region_code":"3366","region_name":"Nghe An","country_code":"264","country_name":"Vietnam"},{"city_code":"32483","city_name":"Thanh Chuong","region_code":"3366","region_name":"Nghe An","country_code":"264","country_name":"Vietnam"},{"city_code":"32484","city_name":"Tuong Duong","region_code":"3366","region_name":"Nghe An","country_code":"264","country_name":"Vietnam"},{"city_code":"32486","city_name":"Yen Thanh","region_code":"3366","region_name":"Nghe An","country_code":"264","country_name":"Vietnam"},{"city_code":"74162","city_name":"Cua Lo Township","region_code":"3366","region_name":"Nghe An","country_code":"264","country_name":"Vietnam"},{"city_code":"74163","city_name":"Vinh City","region_code":"3366","region_name":"Nghe An","country_code":"264","country_name":"Vietnam"}]},{"region_code":"3367","region_name":"Ninh Binh","country_code":"264","country_name":"Vietnam","cities":[{"city_code":"32487","city_name":"Gia Vien","region_code":"3367","region_name":"Ninh Binh","country_code":"264","country_name":"Vietnam"},{"city_code":"32488","city_name":"Hoa Lu","region_code":"3367","region_name":"Ninh Binh","country_code":"264","country_name":"Vietnam"},{"city_code":"32490","city_name":"Kim Son","region_code":"3367","region_name":"Ninh Binh","country_code":"264","country_name":"Vietnam"},{"city_code":"32492","city_name":"Tam Diep Township","region_code":"3367","region_name":"Ninh Binh","country_code":"264","country_name":"Vietnam"},{"city_code":"74164","city_name":"Nho Quan","region_code":"3367","region_name":"Ninh Binh","country_code":"264","country_name":"Vietnam"},{"city_code":"74165","city_name":"Ninh Binh Township","region_code":"3367","region_name":"Ninh Binh","country_code":"264","country_name":"Vietnam"},{"city_code":"74166","city_name":"Yen Khanh","region_code":"3367","region_name":"Ninh Binh","country_code":"264","country_name":"Vietnam"},{"city_code":"74167","city_name":"Yen Mo","region_code":"3367","region_name":"Ninh Binh","country_code":"264","country_name":"Vietnam"}]},{"region_code":"3368","region_name":"Ninh Thuan","country_code":"264","country_name":"Vietnam","cities":[{"city_code":"32493","city_name":"Ninh Hai","region_code":"3368","region_name":"Ninh Thuan","country_code":"264","country_name":"Vietnam"},{"city_code":"32494","city_name":"Ninh Phuoc","region_code":"3368","region_name":"Ninh Thuan","country_code":"264","country_name":"Vietnam"},{"city_code":"32496","city_name":"P.Rang-T.Cham Township","region_code":"3368","region_name":"Ninh Thuan","country_code":"264","country_name":"Vietnam"},{"city_code":"74168","city_name":"Bac Ai","region_code":"3368","region_name":"Ninh Thuan","country_code":"264","country_name":"Vietnam"},{"city_code":"74169","city_name":"Ninh Son","region_code":"3368","region_name":"Ninh Thuan","country_code":"264","country_name":"Vietnam"}]},{"region_code":"3369","region_name":"Phu Tho","country_code":"264","country_name":"Vietnam","cities":[{"city_code":"32498","city_name":"Phu Tho Township","region_code":"3369","region_name":"Phu Tho","country_code":"264","country_name":"Vietnam"},{"city_code":"32499","city_name":"Cam Khe","region_code":"3369","region_name":"Phu Tho","country_code":"264","country_name":"Vietnam"},{"city_code":"32502","city_name":"Thanh Son","region_code":"3369","region_name":"Phu Tho","country_code":"264","country_name":"Vietnam"},{"city_code":"32503","city_name":"Yen Lap","region_code":"3369","region_name":"Phu Tho","country_code":"264","country_name":"Vietnam"},{"city_code":"32665","city_name":"Viet Tri City","region_code":"3369","region_name":"Phu Tho","country_code":"264","country_name":"Vietnam"},{"city_code":"74170","city_name":"Doan Hung","region_code":"3369","region_name":"Phu Tho","country_code":"264","country_name":"Vietnam"},{"city_code":"74171","city_name":"Ha Hoa","region_code":"3369","region_name":"Phu Tho","country_code":"264","country_name":"Vietnam"},{"city_code":"74172","city_name":"Lam Thao","region_code":"3369","region_name":"Phu Tho","country_code":"264","country_name":"Vietnam"},{"city_code":"74173","city_name":"Phu Ninh","region_code":"3369","region_name":"Phu Tho","country_code":"264","country_name":"Vietnam"},{"city_code":"74174","city_name":"Thanh Ba","region_code":"3369","region_name":"Phu Tho","country_code":"264","country_name":"Vietnam"},{"city_code":"74175","city_name":"Thanh Thuy","region_code":"3369","region_name":"Phu Tho","country_code":"264","country_name":"Vietnam"},{"city_code":"74247","city_name":"Tam Nong","region_code":"3369","region_name":"Phu Tho","country_code":"264","country_name":"Vietnam"}]},{"region_code":"3370","region_name":"Phu Yen","country_code":"264","country_name":"Vietnam","cities":[{"city_code":"32504","city_name":"Dong Xuan","region_code":"3370","region_name":"Phu Yen","country_code":"264","country_name":"Vietnam"},{"city_code":"32505","city_name":"Son Hoa","region_code":"3370","region_name":"Phu Yen","country_code":"264","country_name":"Vietnam"},{"city_code":"32506","city_name":"Song Cau","region_code":"3370","region_name":"Phu Yen","country_code":"264","country_name":"Vietnam"},{"city_code":"32507","city_name":"Song Hinh","region_code":"3370","region_name":"Phu Yen","country_code":"264","country_name":"Vietnam"},{"city_code":"32508","city_name":"Tuy An","region_code":"3370","region_name":"Phu Yen","country_code":"264","country_name":"Vietnam"},{"city_code":"32509","city_name":"Tuy Hoa","region_code":"3370","region_name":"Phu Yen","country_code":"264","country_name":"Vietnam"},{"city_code":"74176","city_name":"Phu Hoa","region_code":"3370","region_name":"Phu Yen","country_code":"264","country_name":"Vietnam"},{"city_code":"74177","city_name":"Tuy Hoa Township","region_code":"3370","region_name":"Phu Yen","country_code":"264","country_name":"Vietnam"}]},{"region_code":"3371","region_name":"Quang Binh","country_code":"264","country_name":"Vietnam","cities":[{"city_code":"32511","city_name":"Bo Trach","region_code":"3371","region_name":"Quang Binh","country_code":"264","country_name":"Vietnam"},{"city_code":"32512","city_name":"Dong Hoi City","region_code":"3371","region_name":"Quang Binh","country_code":"264","country_name":"Vietnam"},{"city_code":"32513","city_name":"Le Thuy","region_code":"3371","region_name":"Quang Binh","country_code":"264","country_name":"Vietnam"},{"city_code":"32514","city_name":"Minh Hoa","region_code":"3371","region_name":"Quang Binh","country_code":"264","country_name":"Vietnam"},{"city_code":"32515","city_name":"Quang Ninh","region_code":"3371","region_name":"Quang Binh","country_code":"264","country_name":"Vietnam"},{"city_code":"32516","city_name":"Quang Trach","region_code":"3371","region_name":"Quang Binh","country_code":"264","country_name":"Vietnam"},{"city_code":"32517","city_name":"Tuyen Hoa","region_code":"3371","region_name":"Quang Binh","country_code":"264","country_name":"Vietnam"}]},{"region_code":"3372","region_name":"Quang Nam","country_code":"264","country_name":"Vietnam","cities":[{"city_code":"32518","city_name":"Thang Binh","region_code":"3372","region_name":"Quang Nam","country_code":"264","country_name":"Vietnam"},{"city_code":"32519","city_name":"Dai Loc","region_code":"3372","region_name":"Quang Nam","country_code":"264","country_name":"Vietnam"},{"city_code":"32522","city_name":"Hiep Duc","region_code":"3372","region_name":"Quang Nam","country_code":"264","country_name":"Vietnam"},{"city_code":"32523","city_name":"Hoi An","region_code":"3372","region_name":"Quang Nam","country_code":"264","country_name":"Vietnam"},{"city_code":"32524","city_name":"Nui Thanh","region_code":"3372","region_name":"Quang Nam","country_code":"264","country_name":"Vietnam"},{"city_code":"32525","city_name":"Phuoc Son","region_code":"3372","region_name":"Quang Nam","country_code":"264","country_name":"Vietnam"},{"city_code":"32526","city_name":"Que Son","region_code":"3372","region_name":"Quang Nam","country_code":"264","country_name":"Vietnam"},{"city_code":"32527","city_name":"Tam Ky Township","region_code":"3372","region_name":"Quang Nam","country_code":"264","country_name":"Vietnam"},{"city_code":"32529","city_name":"Tien Phuoc","region_code":"3372","region_name":"Quang Nam","country_code":"264","country_name":"Vietnam"},{"city_code":"74178","city_name":"Bac Tra My","region_code":"3372","region_name":"Quang Nam","country_code":"264","country_name":"Vietnam"},{"city_code":"74179","city_name":"Dien Ban","region_code":"3372","region_name":"Quang Nam","country_code":"264","country_name":"Vietnam"},{"city_code":"74180","city_name":"Dong Giang","region_code":"3372","region_name":"Quang Nam","country_code":"264","country_name":"Vietnam"},{"city_code":"74181","city_name":"Duy Xuyen","region_code":"3372","region_name":"Quang Nam","country_code":"264","country_name":"Vietnam"},{"city_code":"74182","city_name":"Hoi An Township","region_code":"3372","region_name":"Quang Nam","country_code":"264","country_name":"Vietnam"},{"city_code":"74183","city_name":"Nam Giang","region_code":"3372","region_name":"Quang Nam","country_code":"264","country_name":"Vietnam"},{"city_code":"74184","city_name":"Nam Tra My","region_code":"3372","region_name":"Quang Nam","country_code":"264","country_name":"Vietnam"},{"city_code":"74185","city_name":"Tay Giang","region_code":"3372","region_name":"Quang Nam","country_code":"264","country_name":"Vietnam"}]},{"region_code":"3374","region_name":"Quang Ngai","country_code":"264","country_name":"Vietnam","cities":[{"city_code":"32531","city_name":"Ba To","region_code":"3374","region_name":"Quang Ngai","country_code":"264","country_name":"Vietnam"},{"city_code":"32532","city_name":"Binh Son","region_code":"3374","region_name":"Quang Ngai","country_code":"264","country_name":"Vietnam"},{"city_code":"32533","city_name":"Duc Pho","region_code":"3374","region_name":"Quang Ngai","country_code":"264","country_name":"Vietnam"},{"city_code":"32534","city_name":"Minh Long","region_code":"3374","region_name":"Quang Ngai","country_code":"264","country_name":"Vietnam"},{"city_code":"32535","city_name":"Mo Duc","region_code":"3374","region_name":"Quang Ngai","country_code":"264","country_name":"Vietnam"},{"city_code":"32536","city_name":"Nghia Hanh","region_code":"3374","region_name":"Quang Ngai","country_code":"264","country_name":"Vietnam"},{"city_code":"32537","city_name":"Son Ha","region_code":"3374","region_name":"Quang Ngai","country_code":"264","country_name":"Vietnam"},{"city_code":"32538","city_name":"Son Tinh","region_code":"3374","region_name":"Quang Ngai","country_code":"264","country_name":"Vietnam"},{"city_code":"32540","city_name":"Tu Nghia","region_code":"3374","region_name":"Quang Ngai","country_code":"264","country_name":"Vietnam"},{"city_code":"74186","city_name":"Ly Son","region_code":"3374","region_name":"Quang Ngai","country_code":"264","country_name":"Vietnam"},{"city_code":"74187","city_name":"Quang Ngai Township","region_code":"3374","region_name":"Quang Ngai","country_code":"264","country_name":"Vietnam"},{"city_code":"74188","city_name":"Son Tay","region_code":"3374","region_name":"Quang Ngai","country_code":"264","country_name":"Vietnam"},{"city_code":"74189","city_name":"Tay Tra","region_code":"3374","region_name":"Quang Ngai","country_code":"264","country_name":"Vietnam"},{"city_code":"74190","city_name":"Tra Bong","region_code":"3374","region_name":"Quang Ngai","country_code":"264","country_name":"Vietnam"}]},{"region_code":"3375","region_name":"Quang Ninh","country_code":"264","country_name":"Vietnam","cities":[{"city_code":"32542","city_name":"Ba Che","region_code":"3375","region_name":"Quang Ninh","country_code":"264","country_name":"Vietnam"},{"city_code":"32543","city_name":"Binh Lieu","region_code":"3375","region_name":"Quang Ninh","country_code":"264","country_name":"Vietnam"},{"city_code":"32545","city_name":"Cam Pha Township","region_code":"3375","region_name":"Quang Ninh","country_code":"264","country_name":"Vietnam"},{"city_code":"32546","city_name":"Dong Trieu","region_code":"3375","region_name":"Quang Ninh","country_code":"264","country_name":"Vietnam"},{"city_code":"32548","city_name":"Hoanh Bo","region_code":"3375","region_name":"Quang Ninh","country_code":"264","country_name":"Vietnam"},{"city_code":"32551","city_name":"Tien Yen","region_code":"3375","region_name":"Quang Ninh","country_code":"264","country_name":"Vietnam"},{"city_code":"32552","city_name":"Uong Bi Township","region_code":"3375","region_name":"Quang Ninh","country_code":"264","country_name":"Vietnam"},{"city_code":"32553","city_name":"Yen Hung","region_code":"3375","region_name":"Quang Ninh","country_code":"264","country_name":"Vietnam"},{"city_code":"74191","city_name":"Co To","region_code":"3375","region_name":"Quang Ninh","country_code":"264","country_name":"Vietnam"},{"city_code":"74192","city_name":"Dam Ha","region_code":"3375","region_name":"Quang Ninh","country_code":"264","country_name":"Vietnam"},{"city_code":"74193","city_name":"Ha Long City","region_code":"3375","region_name":"Quang Ninh","country_code":"264","country_name":"Vietnam"},{"city_code":"74194","city_name":"Hai Ha","region_code":"3375","region_name":"Quang Ninh","country_code":"264","country_name":"Vietnam"},{"city_code":"74195","city_name":"Mong Cai Township","region_code":"3375","region_name":"Quang Ninh","country_code":"264","country_name":"Vietnam"},{"city_code":"74196","city_name":"Van Don","region_code":"3375","region_name":"Quang Ninh","country_code":"264","country_name":"Vietnam"}]},{"region_code":"3376","region_name":"Quang Tri","country_code":"264","country_name":"Vietnam","cities":[{"city_code":"32555","city_name":"Dong Ha Township","region_code":"3376","region_name":"Quang Tri","country_code":"264","country_name":"Vietnam"},{"city_code":"32556","city_name":"Huong Hoa","region_code":"3376","region_name":"Quang Tri","country_code":"264","country_name":"Vietnam"},{"city_code":"74197","city_name":"Cam Lo","region_code":"3376","region_name":"Quang Tri","country_code":"264","country_name":"Vietnam"},{"city_code":"74198","city_name":"Da Krong","region_code":"3376","region_name":"Quang Tri","country_code":"264","country_name":"Vietnam"},{"city_code":"74199","city_name":"Gio Linh","region_code":"3376","region_name":"Quang Tri","country_code":"264","country_name":"Vietnam"},{"city_code":"74200","city_name":"Hai Lang","region_code":"3376","region_name":"Quang Tri","country_code":"264","country_name":"Vietnam"},{"city_code":"74201","city_name":"Quang Tri Township","region_code":"3376","region_name":"Quang Tri","country_code":"264","country_name":"Vietnam"},{"city_code":"74202","city_name":"Trieu Phong","region_code":"3376","region_name":"Quang Tri","country_code":"264","country_name":"Vietnam"},{"city_code":"74203","city_name":"Vinh Linh","region_code":"3376","region_name":"Quang Tri","country_code":"264","country_name":"Vietnam"}]},{"region_code":"3377","region_name":"Soc Trang","country_code":"264","country_name":"Vietnam","cities":[{"city_code":"32558","city_name":"Ke Sach","region_code":"3377","region_name":"Soc Trang","country_code":"264","country_name":"Vietnam"},{"city_code":"32560","city_name":"My Tu","region_code":"3377","region_name":"Soc Trang","country_code":"264","country_name":"Vietnam"},{"city_code":"32561","city_name":"My Xuyen","region_code":"3377","region_name":"Soc Trang","country_code":"264","country_name":"Vietnam"},{"city_code":"32562","city_name":"Soc Trang Township","region_code":"3377","region_name":"Soc Trang","country_code":"264","country_name":"Vietnam"},{"city_code":"32564","city_name":"Vinh Chau","region_code":"3377","region_name":"Soc Trang","country_code":"264","country_name":"Vietnam"},{"city_code":"74204","city_name":"Cu Lao Dung","region_code":"3377","region_name":"Soc Trang","country_code":"264","country_name":"Vietnam"},{"city_code":"74205","city_name":"Long Phu","region_code":"3377","region_name":"Soc Trang","country_code":"264","country_name":"Vietnam"},{"city_code":"74206","city_name":"Nga Nam","region_code":"3377","region_name":"Soc Trang","country_code":"264","country_name":"Vietnam"},{"city_code":"74207","city_name":"Thanh Tri","region_code":"3377","region_name":"Soc Trang","country_code":"264","country_name":"Vietnam"}]},{"region_code":"3378","region_name":"Son La","country_code":"264","country_name":"Vietnam","cities":[{"city_code":"32565","city_name":"Bac Yen","region_code":"3378","region_name":"Son La","country_code":"264","country_name":"Vietnam"},{"city_code":"32566","city_name":"Mai Son","region_code":"3378","region_name":"Son La","country_code":"264","country_name":"Vietnam"},{"city_code":"32567","city_name":"Moc Chau","region_code":"3378","region_name":"Son La","country_code":"264","country_name":"Vietnam"},{"city_code":"32568","city_name":"Muong La","region_code":"3378","region_name":"Son La","country_code":"264","country_name":"Vietnam"},{"city_code":"32569","city_name":"Phu Yen","region_code":"3378","region_name":"Son La","country_code":"264","country_name":"Vietnam"},{"city_code":"32570","city_name":"Quynh Nhai","region_code":"3378","region_name":"Son La","country_code":"264","country_name":"Vietnam"},{"city_code":"32572","city_name":"Thuan Chau","region_code":"3378","region_name":"Son La","country_code":"264","country_name":"Vietnam"},{"city_code":"32574","city_name":"Yen Chau","region_code":"3378","region_name":"Son La","country_code":"264","country_name":"Vietnam"},{"city_code":"74208","city_name":"Son La Township","region_code":"3378","region_name":"Son La","country_code":"264","country_name":"Vietnam"},{"city_code":"74209","city_name":"Song Ma","region_code":"3378","region_name":"Son La","country_code":"264","country_name":"Vietnam"},{"city_code":"74210","city_name":"Sop Cop","region_code":"3378","region_name":"Son La","country_code":"264","country_name":"Vietnam"}]},{"region_code":"3379","region_name":"Tay Ninh","country_code":"264","country_name":"Vietnam","cities":[{"city_code":"32575","city_name":"Ben Cau","region_code":"3379","region_name":"Tay Ninh","country_code":"264","country_name":"Vietnam"},{"city_code":"32576","city_name":"Chau Thanh","region_code":"3379","region_name":"Tay Ninh","country_code":"264","country_name":"Vietnam"},{"city_code":"32578","city_name":"Go Dau","region_code":"3379","region_name":"Tay Ninh","country_code":"264","country_name":"Vietnam"},{"city_code":"32580","city_name":"Tan Bien","region_code":"3379","region_name":"Tay Ninh","country_code":"264","country_name":"Vietnam"},{"city_code":"32581","city_name":"Tan Chau","region_code":"3379","region_name":"Tay Ninh","country_code":"264","country_name":"Vietnam"},{"city_code":"32582","city_name":"Trang Bang","region_code":"3379","region_name":"Tay Ninh","country_code":"264","country_name":"Vietnam"},{"city_code":"74211","city_name":"DMinh Chau","region_code":"3379","region_name":"Tay Ninh","country_code":"264","country_name":"Vietnam"},{"city_code":"74212","city_name":"Hoa Thanh","region_code":"3379","region_name":"Tay Ninh","country_code":"264","country_name":"Vietnam"},{"city_code":"74213","city_name":"Tay Ninh Township","region_code":"3379","region_name":"Tay Ninh","country_code":"264","country_name":"Vietnam"}]},{"region_code":"3380","region_name":"Thai Binh","country_code":"264","country_name":"Vietnam","cities":[{"city_code":"32584","city_name":"Dong Hung","region_code":"3380","region_name":"Thai Binh","country_code":"264","country_name":"Vietnam"},{"city_code":"32585","city_name":"Hung Ha","region_code":"3380","region_name":"Thai Binh","country_code":"264","country_name":"Vietnam"},{"city_code":"32586","city_name":"Kien Xuong","region_code":"3380","region_name":"Thai Binh","country_code":"264","country_name":"Vietnam"},{"city_code":"32587","city_name":"Quynh Phu","region_code":"3380","region_name":"Thai Binh","country_code":"264","country_name":"Vietnam"},{"city_code":"32588","city_name":"Thai Thuy","region_code":"3380","region_name":"Thai Binh","country_code":"264","country_name":"Vietnam"},{"city_code":"32589","city_name":"Tien Hai","region_code":"3380","region_name":"Thai Binh","country_code":"264","country_name":"Vietnam"},{"city_code":"74214","city_name":"Thai Binh City","region_code":"3380","region_name":"Thai Binh","country_code":"264","country_name":"Vietnam"},{"city_code":"74215","city_name":"Vu Thu","region_code":"3380","region_name":"Thai Binh","country_code":"264","country_name":"Vietnam"}]},{"region_code":"3381","region_name":"Thai Nguyen","country_code":"264","country_name":"Vietnam","cities":[{"city_code":"32591","city_name":"Dai Tu","region_code":"3381","region_name":"Thai Nguyen","country_code":"264","country_name":"Vietnam"},{"city_code":"32592","city_name":"Dinh Hoa","region_code":"3381","region_name":"Thai Nguyen","country_code":"264","country_name":"Vietnam"},{"city_code":"32593","city_name":"Dong Hy","region_code":"3381","region_name":"Thai Nguyen","country_code":"264","country_name":"Vietnam"},{"city_code":"32594","city_name":"Pho Yen","region_code":"3381","region_name":"Thai Nguyen","country_code":"264","country_name":"Vietnam"},{"city_code":"32595","city_name":"Phu Binh","region_code":"3381","region_name":"Thai Nguyen","country_code":"264","country_name":"Vietnam"},{"city_code":"32596","city_name":"Phu Luong","region_code":"3381","region_name":"Thai Nguyen","country_code":"264","country_name":"Vietnam"},{"city_code":"32597","city_name":"Song Cong Township","region_code":"3381","region_name":"Thai Nguyen","country_code":"264","country_name":"Vietnam"},{"city_code":"32599","city_name":"Vo Nhai","region_code":"3381","region_name":"Thai Nguyen","country_code":"264","country_name":"Vietnam"},{"city_code":"74216","city_name":"Thai Nguyen City","region_code":"3381","region_name":"Thai Nguyen","country_code":"264","country_name":"Vietnam"}]},{"region_code":"3382","region_name":"Thanh Hoa","country_code":"264","country_name":"Vietnam","cities":[{"city_code":"32600","city_name":"Ba Thuoc","region_code":"3382","region_name":"Thanh Hoa","country_code":"264","country_name":"Vietnam"},{"city_code":"32601","city_name":"Bim Son Township","region_code":"3382","region_name":"Thanh Hoa","country_code":"264","country_name":"Vietnam"},{"city_code":"32602","city_name":"Cam Thuy","region_code":"3382","region_name":"Thanh Hoa","country_code":"264","country_name":"Vietnam"},{"city_code":"32603","city_name":"Hau Loc","region_code":"3382","region_name":"Thanh Hoa","country_code":"264","country_name":"Vietnam"},{"city_code":"32604","city_name":"Hoang Hoa","region_code":"3382","region_name":"Thanh Hoa","country_code":"264","country_name":"Vietnam"},{"city_code":"32605","city_name":"Lang Chanh","region_code":"3382","region_name":"Thanh Hoa","country_code":"264","country_name":"Vietnam"},{"city_code":"32606","city_name":"Nga Son","region_code":"3382","region_name":"Thanh Hoa","country_code":"264","country_name":"Vietnam"},{"city_code":"32607","city_name":"Nhu Xuan","region_code":"3382","region_name":"Thanh Hoa","country_code":"264","country_name":"Vietnam"},{"city_code":"32608","city_name":"Nong Cong","region_code":"3382","region_name":"Thanh Hoa","country_code":"264","country_name":"Vietnam"},{"city_code":"32609","city_name":"Quan Hoa","region_code":"3382","region_name":"Thanh Hoa","country_code":"264","country_name":"Vietnam"},{"city_code":"32610","city_name":"Quang Xuong","region_code":"3382","region_name":"Thanh Hoa","country_code":"264","country_name":"Vietnam"},{"city_code":"32611","city_name":"Sam Son Township","region_code":"3382","region_name":"Thanh Hoa","country_code":"264","country_name":"Vietnam"},{"city_code":"32612","city_name":"Thach Thanh","region_code":"3382","region_name":"Thanh Hoa","country_code":"264","country_name":"Vietnam"},{"city_code":"32614","city_name":"Tho Xuan","region_code":"3382","region_name":"Thanh Hoa","country_code":"264","country_name":"Vietnam"},{"city_code":"32615","city_name":"Thuong Xuan","region_code":"3382","region_name":"Thanh Hoa","country_code":"264","country_name":"Vietnam"},{"city_code":"32616","city_name":"Tinh Gia","region_code":"3382","region_name":"Thanh Hoa","country_code":"264","country_name":"Vietnam"},{"city_code":"32617","city_name":"Trieu Son","region_code":"3382","region_name":"Thanh Hoa","country_code":"264","country_name":"Vietnam"},{"city_code":"32619","city_name":"Vinh Loc","region_code":"3382","region_name":"Thanh Hoa","country_code":"264","country_name":"Vietnam"},{"city_code":"74217","city_name":"Dong Son","region_code":"3382","region_name":"Thanh Hoa","country_code":"264","country_name":"Vietnam"},{"city_code":"74218","city_name":"Ha Trung","region_code":"3382","region_name":"Thanh Hoa","country_code":"264","country_name":"Vietnam"},{"city_code":"74219","city_name":"Muong Lat","region_code":"3382","region_name":"Thanh Hoa","country_code":"264","country_name":"Vietnam"},{"city_code":"74220","city_name":"Ngoc Lac","region_code":"3382","region_name":"Thanh Hoa","country_code":"264","country_name":"Vietnam"},{"city_code":"74221","city_name":"Nhu Thanh","region_code":"3382","region_name":"Thanh Hoa","country_code":"264","country_name":"Vietnam"},{"city_code":"74222","city_name":"Quan Son","region_code":"3382","region_name":"Thanh Hoa","country_code":"264","country_name":"Vietnam"},{"city_code":"74223","city_name":"Thanh Hoa City","region_code":"3382","region_name":"Thanh Hoa","country_code":"264","country_name":"Vietnam"},{"city_code":"74224","city_name":"Thieu Hoa","region_code":"3382","region_name":"Thanh Hoa","country_code":"264","country_name":"Vietnam"},{"city_code":"74225","city_name":"Yen Dinh","region_code":"3382","region_name":"Thanh Hoa","country_code":"264","country_name":"Vietnam"}]},{"region_code":"3383","region_name":"Thua Thien - Hue","country_code":"264","country_name":"Vietnam","cities":[{"city_code":"32620","city_name":"A Luoi","region_code":"3383","region_name":"Thua Thien - Hue","country_code":"264","country_name":"Vietnam"},{"city_code":"32621","city_name":"Hue City","region_code":"3383","region_name":"Thua Thien - Hue","country_code":"264","country_name":"Vietnam"},{"city_code":"32622","city_name":"Huong Thuy","region_code":"3383","region_name":"Thua Thien - Hue","country_code":"264","country_name":"Vietnam"},{"city_code":"32623","city_name":"Huong Tra","region_code":"3383","region_name":"Thua Thien - Hue","country_code":"264","country_name":"Vietnam"},{"city_code":"32624","city_name":"Nam Dong","region_code":"3383","region_name":"Thua Thien - Hue","country_code":"264","country_name":"Vietnam"},{"city_code":"32625","city_name":"Phong Dien","region_code":"3383","region_name":"Thua Thien - Hue","country_code":"264","country_name":"Vietnam"},{"city_code":"32626","city_name":"Phu Loc","region_code":"3383","region_name":"Thua Thien - Hue","country_code":"264","country_name":"Vietnam"},{"city_code":"32627","city_name":"Phu Vang","region_code":"3383","region_name":"Thua Thien - Hue","country_code":"264","country_name":"Vietnam"},{"city_code":"32628","city_name":"Quang Dien","region_code":"3383","region_name":"Thua Thien - Hue","country_code":"264","country_name":"Vietnam"}]},{"region_code":"3384","region_name":"Tien Giang","country_code":"264","country_name":"Vietnam","cities":[{"city_code":"32629","city_name":"Cai Lay","region_code":"3384","region_name":"Tien Giang","country_code":"264","country_name":"Vietnam"},{"city_code":"32630","city_name":"Chau Thanh","region_code":"3384","region_name":"Tien Giang","country_code":"264","country_name":"Vietnam"},{"city_code":"32632","city_name":"Go Cong Dong","region_code":"3384","region_name":"Tien Giang","country_code":"264","country_name":"Vietnam"},{"city_code":"32633","city_name":"Go Cong Tay","region_code":"3384","region_name":"Tien Giang","country_code":"264","country_name":"Vietnam"},{"city_code":"74226","city_name":"Cai Be","region_code":"3384","region_name":"Tien Giang","country_code":"264","country_name":"Vietnam"},{"city_code":"74227","city_name":"Cho Gao","region_code":"3384","region_name":"Tien Giang","country_code":"264","country_name":"Vietnam"},{"city_code":"74228","city_name":"Go Cong Township","region_code":"3384","region_name":"Tien Giang","country_code":"264","country_name":"Vietnam"},{"city_code":"74229","city_name":"My Tho City","region_code":"3384","region_name":"Tien Giang","country_code":"264","country_name":"Vietnam"},{"city_code":"74230","city_name":"Tan Phuoc","region_code":"3384","region_name":"Tien Giang","country_code":"264","country_name":"Vietnam"}]},{"region_code":"3386","region_name":"Tra Vinh","country_code":"264","country_name":"Vietnam","cities":[{"city_code":"32642","city_name":"Cang Long","region_code":"3386","region_name":"Tra Vinh","country_code":"264","country_name":"Vietnam"},{"city_code":"32643","city_name":"Cau Ke","region_code":"3386","region_name":"Tra Vinh","country_code":"264","country_name":"Vietnam"},{"city_code":"32644","city_name":"Cau Ngang","region_code":"3386","region_name":"Tra Vinh","country_code":"264","country_name":"Vietnam"},{"city_code":"32645","city_name":"Chau Thanh","region_code":"3386","region_name":"Tra Vinh","country_code":"264","country_name":"Vietnam"},{"city_code":"32647","city_name":"Tieu Can","region_code":"3386","region_name":"Tra Vinh","country_code":"264","country_name":"Vietnam"},{"city_code":"32648","city_name":"Tra Cu","region_code":"3386","region_name":"Tra Vinh","country_code":"264","country_name":"Vietnam"},{"city_code":"32649","city_name":"Tra Vinh Township","region_code":"3386","region_name":"Tra Vinh","country_code":"264","country_name":"Vietnam"},{"city_code":"74231","city_name":"Duyen Hai","region_code":"3386","region_name":"Tra Vinh","country_code":"264","country_name":"Vietnam"}]},{"region_code":"3387","region_name":"Tuyen Quang","country_code":"264","country_name":"Vietnam","cities":[{"city_code":"32650","city_name":"Chiem Hoa","region_code":"3387","region_name":"Tuyen Quang","country_code":"264","country_name":"Vietnam"},{"city_code":"32651","city_name":"Ham Yen","region_code":"3387","region_name":"Tuyen Quang","country_code":"264","country_name":"Vietnam"},{"city_code":"32652","city_name":"Na Hang","region_code":"3387","region_name":"Tuyen Quang","country_code":"264","country_name":"Vietnam"},{"city_code":"32653","city_name":"Son Duong","region_code":"3387","region_name":"Tuyen Quang","country_code":"264","country_name":"Vietnam"},{"city_code":"32655","city_name":"Yen Son","region_code":"3387","region_name":"Tuyen Quang","country_code":"264","country_name":"Vietnam"},{"city_code":"74232","city_name":"Tuyen Quang Township","region_code":"3387","region_name":"Tuyen Quang","country_code":"264","country_name":"Vietnam"}]},{"region_code":"3388","region_name":"Vinh Long","country_code":"264","country_name":"Vietnam","cities":[{"city_code":"32656","city_name":"Binh Minh","region_code":"3388","region_name":"Vinh Long","country_code":"264","country_name":"Vietnam"},{"city_code":"32657","city_name":"Long Ho","region_code":"3388","region_name":"Vinh Long","country_code":"264","country_name":"Vietnam"},{"city_code":"32658","city_name":"Tam Binh","region_code":"3388","region_name":"Vinh Long","country_code":"264","country_name":"Vietnam"},{"city_code":"32659","city_name":"Tra on","region_code":"3388","region_name":"Vinh Long","country_code":"264","country_name":"Vietnam"},{"city_code":"32660","city_name":"Vinh Long Township","region_code":"3388","region_name":"Vinh Long","country_code":"264","country_name":"Vietnam"},{"city_code":"32661","city_name":"Vung Liem","region_code":"3388","region_name":"Vinh Long","country_code":"264","country_name":"Vietnam"},{"city_code":"74233","city_name":"Mang Thit","region_code":"3388","region_name":"Vinh Long","country_code":"264","country_name":"Vietnam"}]},{"region_code":"3389","region_name":"Vinh Phuc","country_code":"264","country_name":"Vietnam","cities":[{"city_code":"74234","city_name":"Binh Xuyen","region_code":"3389","region_name":"Vinh Phuc","country_code":"264","country_name":"Vietnam"},{"city_code":"74235","city_name":"Lap Thach","region_code":"3389","region_name":"Vinh Phuc","country_code":"264","country_name":"Vietnam"},{"city_code":"74236","city_name":"Me Linh","region_code":"3389","region_name":"Vinh Phuc","country_code":"264","country_name":"Vietnam"},{"city_code":"74237","city_name":"Phuc Yen township","region_code":"3389","region_name":"Vinh Phuc","country_code":"264","country_name":"Vietnam"},{"city_code":"74238","city_name":"Tam Dao","region_code":"3389","region_name":"Vinh Phuc","country_code":"264","country_name":"Vietnam"},{"city_code":"74239","city_name":"Tam Duong","region_code":"3389","region_name":"Vinh Phuc","country_code":"264","country_name":"Vietnam"},{"city_code":"74240","city_name":"Vinh Tuong","region_code":"3389","region_name":"Vinh Phuc","country_code":"264","country_name":"Vietnam"},{"city_code":"74241","city_name":"Vinh Yen Township","region_code":"3389","region_name":"Vinh Phuc","country_code":"264","country_name":"Vietnam"},{"city_code":"74242","city_name":"Yen Lac","region_code":"3389","region_name":"Vinh Phuc","country_code":"264","country_name":"Vietnam"}]},{"region_code":"3390","region_name":"Yen Bai","country_code":"264","country_name":"Vietnam","cities":[{"city_code":"32668","city_name":"Luc Yen","region_code":"3390","region_name":"Yen Bai","country_code":"264","country_name":"Vietnam"},{"city_code":"32669","city_name":"Mu Cang Chai","region_code":"3390","region_name":"Yen Bai","country_code":"264","country_name":"Vietnam"},{"city_code":"32670","city_name":"Tram Tau","region_code":"3390","region_name":"Yen Bai","country_code":"264","country_name":"Vietnam"},{"city_code":"32671","city_name":"Tran Yen","region_code":"3390","region_name":"Yen Bai","country_code":"264","country_name":"Vietnam"},{"city_code":"32673","city_name":"Van Chan","region_code":"3390","region_name":"Yen Bai","country_code":"264","country_name":"Vietnam"},{"city_code":"32674","city_name":"Van Yen","region_code":"3390","region_name":"Yen Bai","country_code":"264","country_name":"Vietnam"},{"city_code":"32675","city_name":"Yen Binh","region_code":"3390","region_name":"Yen Bai","country_code":"264","country_name":"Vietnam"},{"city_code":"74243","city_name":"Nghia Lo Township","region_code":"3390","region_name":"Yen Bai","country_code":"264","country_name":"Vietnam"},{"city_code":"74244","city_name":"Yen Bai City","region_code":"3390","region_name":"Yen Bai","country_code":"264","country_name":"Vietnam"}]},{"region_code":"73933","region_name":"Can Tho city","country_code":"264","country_name":"Vietnam","cities":[{"city_code":"73975","city_name":"Binh Thuy","region_code":"73933","region_name":"Can Tho city","country_code":"264","country_name":"Vietnam"},{"city_code":"73976","city_name":"Cai Rang","region_code":"73933","region_name":"Can Tho city","country_code":"264","country_name":"Vietnam"},{"city_code":"73977","city_name":"Co Do","region_code":"73933","region_name":"Can Tho city","country_code":"264","country_name":"Vietnam"},{"city_code":"73978","city_name":"Ninh Kieu","region_code":"73933","region_name":"Can Tho city","country_code":"264","country_name":"Vietnam"},{"city_code":"73979","city_name":"Phong Dien","region_code":"73933","region_name":"Can Tho city","country_code":"264","country_name":"Vietnam"},{"city_code":"73980","city_name":"Thot Not","region_code":"73933","region_name":"Can Tho city","country_code":"264","country_name":"Vietnam"},{"city_code":"73981","city_name":"Vinh Thanh","region_code":"73933","region_name":"Can Tho city","country_code":"264","country_name":"Vietnam"},{"city_code":"73982","city_name":"o Mon","region_code":"73933","region_name":"Can Tho city","country_code":"264","country_name":"Vietnam"}]},{"region_code":"73934","region_name":"Dak Lak","country_code":"264","country_name":"Vietnam","cities":[{"city_code":"32275","city_name":"Cu M'gar","region_code":"73934","region_name":"Dak Lak","country_code":"264","country_name":"Vietnam"},{"city_code":"32280","city_name":"Krong A Na","region_code":"73934","region_name":"Dak Lak","country_code":"264","country_name":"Vietnam"},{"city_code":"32281","city_name":"Krong Bong","region_code":"73934","region_name":"Dak Lak","country_code":"264","country_name":"Vietnam"},{"city_code":"32282","city_name":"Krong Buk","region_code":"73934","region_name":"Dak Lak","country_code":"264","country_name":"Vietnam"},{"city_code":"32283","city_name":"Krong Nang","region_code":"73934","region_name":"Dak Lak","country_code":"264","country_name":"Vietnam"},{"city_code":"32285","city_name":"Krong Pak","region_code":"73934","region_name":"Dak Lak","country_code":"264","country_name":"Vietnam"},{"city_code":"32287","city_name":"M'Drak","region_code":"73934","region_name":"Dak Lak","country_code":"264","country_name":"Vietnam"},{"city_code":"73994","city_name":"Buon Don","region_code":"73934","region_name":"Dak Lak","country_code":"264","country_name":"Vietnam"},{"city_code":"73995","city_name":"Buon Ma Thuot City","region_code":"73934","region_name":"Dak Lak","country_code":"264","country_name":"Vietnam"},{"city_code":"73996","city_name":"Ea H'leo","region_code":"73934","region_name":"Dak Lak","country_code":"264","country_name":"Vietnam"},{"city_code":"73997","city_name":"Ea Kar","region_code":"73934","region_name":"Dak Lak","country_code":"264","country_name":"Vietnam"},{"city_code":"73998","city_name":"Ea Sup","region_code":"73934","region_name":"Dak Lak","country_code":"264","country_name":"Vietnam"},{"city_code":"73999","city_name":"Lak","region_code":"73934","region_name":"Dak Lak","country_code":"264","country_name":"Vietnam"}]},{"region_code":"73935","region_name":"Dak Nong","country_code":"264","country_name":"Vietnam","cities":[{"city_code":"74001","city_name":"Cu Jut","region_code":"73935","region_name":"Dak Nong","country_code":"264","country_name":"Vietnam"},{"city_code":"74002","city_name":"Dak Mil","region_code":"73935","region_name":"Dak Nong","country_code":"264","country_name":"Vietnam"},{"city_code":"74003","city_name":"Dak Nong","region_code":"73935","region_name":"Dak Nong","country_code":"264","country_name":"Vietnam"},{"city_code":"74004","city_name":"Dak R'Lap","region_code":"73935","region_name":"Dak Nong","country_code":"264","country_name":"Vietnam"},{"city_code":"74005","city_name":"Dak Song","region_code":"73935","region_name":"Dak Nong","country_code":"264","country_name":"Vietnam"},{"city_code":"74006","city_name":"Krong No","region_code":"73935","region_name":"Dak Nong","country_code":"264","country_name":"Vietnam"}]},{"region_code":"73936","region_name":"Dien Bien","country_code":"264","country_name":"Vietnam","cities":[{"city_code":"32416","city_name":"Tua Chua","region_code":"73936","region_name":"Dien Bien","country_code":"264","country_name":"Vietnam"},{"city_code":"32417","city_name":"Tuan Giao","region_code":"73936","region_name":"Dien Bien","country_code":"264","country_name":"Vietnam"},{"city_code":"74008","city_name":"D.Bien","region_code":"73936","region_name":"Dien Bien","country_code":"264","country_name":"Vietnam"},{"city_code":"74009","city_name":"D.Bien Dong","region_code":"73936","region_name":"Dien Bien","country_code":"264","country_name":"Vietnam"},{"city_code":"74010","city_name":"Dien Bien Phu City","region_code":"73936","region_name":"Dien Bien","country_code":"264","country_name":"Vietnam"},{"city_code":"74011","city_name":"Muong Lay Township","region_code":"73936","region_name":"Dien Bien","country_code":"264","country_name":"Vietnam"},{"city_code":"74012","city_name":"Muong Lay","region_code":"73936","region_name":"Dien Bien","country_code":"264","country_name":"Vietnam"},{"city_code":"74013","city_name":"Muong Nhe","region_code":"73936","region_name":"Dien Bien","country_code":"264","country_name":"Vietnam"}]},{"region_code":"73937","region_name":"Hau Giang","country_code":"264","country_name":"Vietnam","cities":[{"city_code":"32249","city_name":"Long My","region_code":"73937","region_name":"Hau Giang","country_code":"264","country_name":"Vietnam"},{"city_code":"32251","city_name":"Phung Hiep","region_code":"73937","region_name":"Hau Giang","country_code":"264","country_name":"Vietnam"},{"city_code":"32253","city_name":"Vi Thanh Township","region_code":"73937","region_name":"Hau Giang","country_code":"264","country_name":"Vietnam"},{"city_code":"74096","city_name":"Cai Rang","region_code":"73937","region_name":"Hau Giang","country_code":"264","country_name":"Vietnam"},{"city_code":"74097","city_name":"Chau Thanh","region_code":"73937","region_name":"Hau Giang","country_code":"264","country_name":"Vietnam"},{"city_code":"74098","city_name":"Chau Thanh A","region_code":"73937","region_name":"Hau Giang","country_code":"264","country_name":"Vietnam"},{"city_code":"74100","city_name":"Vi Thuy","region_code":"73937","region_name":"Hau Giang","country_code":"264","country_name":"Vietnam"}]},{"region_code":"73938","region_name":"Lai Chau","country_code":"264","country_name":"Vietnam","cities":[{"city_code":"74140","city_name":"Lai Chau township","region_code":"73938","region_name":"Lai Chau","country_code":"264","country_name":"Vietnam"},{"city_code":"74141","city_name":"Muong Te","region_code":"73938","region_name":"Lai Chau","country_code":"264","country_name":"Vietnam"},{"city_code":"74142","city_name":"Phong Tho","region_code":"73938","region_name":"Lai Chau","country_code":"264","country_name":"Vietnam"},{"city_code":"74143","city_name":"Sin Ho","region_code":"73938","region_name":"Lai Chau","country_code":"264","country_name":"Vietnam"},{"city_code":"74144","city_name":"Tam Duong","region_code":"73938","region_name":"Lai Chau","country_code":"264","country_name":"Vietnam"},{"city_code":"74145","city_name":"Thanh Uyen","region_code":"73938","region_name":"Lai Chau","country_code":"264","country_name":"Vietnam"}]},{"region_code":"73939","region_name":"Lao Cai","country_code":"264","country_name":"Vietnam","cities":[{"city_code":"32441","city_name":"Bao Thang","region_code":"73939","region_name":"Lao Cai","country_code":"264","country_name":"Vietnam"},{"city_code":"32442","city_name":"Bat Xat","region_code":"73939","region_name":"Lao Cai","country_code":"264","country_name":"Vietnam"},{"city_code":"32443","city_name":"Muong Khuong","region_code":"73939","region_name":"Lao Cai","country_code":"264","country_name":"Vietnam"},{"city_code":"32444","city_name":"Sa Pa","region_code":"73939","region_name":"Lao Cai","country_code":"264","country_name":"Vietnam"},{"city_code":"32447","city_name":"Van Ban","region_code":"73939","region_name":"Lao Cai","country_code":"264","country_name":"Vietnam"},{"city_code":"74150","city_name":"Bac Ha","region_code":"73939","region_name":"Lao Cai","country_code":"264","country_name":"Vietnam"},{"city_code":"74151","city_name":"Bao Yen","region_code":"73939","region_name":"Lao Cai","country_code":"264","country_name":"Vietnam"},{"city_code":"74152","city_name":"Lao Cai City","region_code":"73939","region_name":"Lao Cai","country_code":"264","country_name":"Vietnam"},{"city_code":"74153","city_name":"Si Ma Cai","region_code":"73939","region_name":"Lao Cai","country_code":"264","country_name":"Vietnam"}]}]}