{"country_code":"83","country_name":"Fiji","country_iso2":"FJ","country_iso3":"FJI","regions":[{"region_code":"40187","region_name":"Central","country_code":"83","country_name":"Fiji","cities":[{"city_code":"40191","city_name":"Naitasiri","region_code":"40187","region_name":"Central","country_code":"83","country_name":"Fiji"},{"city_code":"40192","city_name":"Namosi","region_code":"40187","region_name":"Central","country_code":"83","country_name":"Fiji"},{"city_code":"40193","city_name":"Rewa","region_code":"40187","region_name":"Central","country_code":"83","country_name":"Fiji"},{"city_code":"40194","city_name":"Serua","region_code":"40187","region_name":"Central","country_code":"83","country_name":"Fiji"},{"city_code":"40195","city_name":"Tailevu","region_code":"40187","region_name":"Central","country_code":"83","country_name":"Fiji"}]},{"region_code":"40188","region_name":"Eastern","country_code":"83","country_name":"Fiji","cities":[{"city_code":"40196","city_name":"Kadavu","region_code":"40188","region_name":"Eastern","country_code":"83","country_name":"Fiji"},{"city_code":"40197","city_name":"Lau","region_code":"40188","region_name":"Eastern","country_code":"83","country_name":"Fiji"},{"city_code":"40198","city_name":"Lomaiviti","region_code":"40188","region_name":"Eastern","country_code":"83","country_name":"Fiji"},{"city_code":"40199","city_name":"Rotuma","region_code":"40188","region_name":"Eastern","country_code":"83","country_name":"Fiji"}]},{"region_code":"40189","region_name":"Northern","country_code":"83","country_name":"Fiji","cities":[{"city_code":"40200","city_name":"Bua","region_code":"40189","region_name":"Northern","country_code":"83","country_name":"Fiji"},{"city_code":"40201","city_name":"Cakaudrove","region_code":"40189","region_name":"Northern","country_code":"83","country_name":"Fiji"},{"city_code":"40202","city_name":"Macuata","region_code":"40189","region_name":"Northern","country_code":"83","country_name":"Fiji"}]},{"region_code":"40190","region_name":"Western","country_code":"83","country_name":"Fiji","cities":[{"city_code":"40203","city_name":"Ba","region_code":"40190","region_name":"Western","country_code":"83","country_name":"Fiji"},{"city_code":"40204","city_name":"Nadroga & Navosa","region_code":"40190","region_name":"Western","country_code":"83","country_name":"Fiji"},{"city_code":"40205","city_name":"Ra","region_code":"40190","region_name":"Western","country_code":"83","country_name":"Fiji"}]}]}